Workbook

Sheet Capa

Sheet 1. Dados Históricos
A1: 1. Retornos Históricos | F1: 2. Medidas da Amostra Histórica | K1: 3. Possíveis Portifólios entre as Classes | R1: 4. Modern Portfolio Theory – MPT e Cálculos
A2: Ano | B2: Private Equity Returns | C2: S&P500 | D2: Treasury Bond (10 anos) | K2: wPrivate | L2: wS&P500 | M2: wTreasury | N2: Total | O2: Desvio Padrão do Portifolio | P2: Retorno Esperado do Portifolio | Z2: Portifólio de Variância Mínima Global | AG2: Portifólio de Aplicação Ótima
A3: 1995 | B3: 0.23906608 | C3: 0.37195199 | D3: 0.2348078 | F3: Medidas | G3: Private Equity Returns | H3: S&P500 | I3: Treasury Bond (10 anos) | K3: 0 | L3: {=_xlfn.SEQUENCE(21,,0,5%)} -> 0 | M3: =1-K3-L3 -> 1 | N3: =SUM(K3:M3) -> 1 | O3: =SQRT(K3^2*$G$4^2 + L3^2*$H$4^2 + M3^2*$I$4^2 + 2*K3*L3*$G$10*$G$4*$H$4 + 2*L3*M3*$G$12*$H$4*$I$4 + 2*K3*M3*$G$11*$G$4*$I$4) -> 0.094481262 | P3: =K3*$G$7 + L3*$H$7 + M3*$I$7 -> 0.034 | Z3: wPrivate | AA3: wS&P500 | AB3: wTreasury | AC3: Total | AD3: Desvio Padrão do Portifolio | AE3: Retorno Esperado do Portifolio | AG3: wPrivate | AH3: wS&P500 | AI3: wTreasury | AJ3: Total | AK3: Desvio Padrão do Portifolio | AL3: Retorno Esperado do Portifolio
A4: 1996 | B4: 0.30387514 | C4: 0.22680966 | D4: 0.014286078 | F4: Desvio Padrão | G4: =_xlfn.STDEV.S(Tabela3[Private Equity Returns]) -> 0.15294529 | H4: =_xlfn.STDEV.S(Tabela3[S&P500]) -> 0.18162652 | I4: =_xlfn.STDEV.S(Tabela3[Treasury Bond (10 anos)]) -> 0.094481262 | K4: 0 | L4: 0.05 | M4: =1-K4-L4 -> 0.95 | N4: =SUM(K4:M4) -> 1 | O4: =SQRT(K4^2*$G$4^2 + L4^2*$H$4^2 + M4^2*$I$4^2 + 2*K4*L4*$G$10*$G$4*$H$4 + 2*L4*M4*$G$12*$H$4*$I$4 + 2*K4*M4*$G$11*$G$4*$I$4) -> 0.088730951 | P4: =K4*$G$7 + L4*$H$7 + M4*$I$7 -> 0.035275 | Z4: 0.21207041 | AA4: 0.090413347 | AB4: 0.69751624 | AC4: =SUM(Z4:AB4) -> 1 | AD4: =SQRT(Z4^2*$G$4^2 + AA4^2*$H$4^2 + AB4^2*$I$4^2 + 2*Z4*AA4*$G$10*$G$4*$H$4 + 2*AA4*AB4*$G$12*$H$4*$I$4 + 2*Z4*AB4*$G$11*$G$4*$I$4) -> 0.074638252 | AE4: =Z4*$G$7 + AA4*$H$7 + AB4*$I$7 -> 0.050726328 | AG4: 0.99743851 | AH4: 0 | AI4: 0.0025614855 | AJ4: =SUM(AG4:AI4) -> 1 | AK4: =SQRT(AG4^2*$G$4^2 + AH4^2*$H$4^2 + AI4^2*$I$4^2 + 2*AG4*AH4*$G$10*$G$4*$H$4 + 2*AH4*AI4*$G$12*$H$4*$I$4 + 2*AG4*AI4*$G$11*$G$4*$I$4) -> 0.1525219 | AL4: =AG4*$G$7 + AH4*$H$7 + AI4*$I$7 -> 0.10182582
A5: 1997 | B5: 0.28713348 | C5: 0.33103653 | D5: 0.099391303 | F5: Retorno Histórico | G5: =AVERAGE(Tabela3[Private Equity Returns]) -> 0.15367828 | H5: =AVERAGE(Tabela3[S&P500]) -> 0.12446147 | I5: =AVERAGE(Tabela3[Treasury Bond (10 anos)]) -> 0.047528699 | K5: 0 | L5: 0.1 | M5: =1-K5-L5 -> 0.9 | N5: =SUM(K5:M5) -> 1 | O5: =SQRT(K5^2*$G$4^2 + L5^2*$H$4^2 + M5^2*$I$4^2 + 2*K5*L5*$G$10*$G$4*$H$4 + 2*L5*M5*$G$12*$H$4*$I$4 + 2*K5*M5*$G$11*$G$4*$I$4) -> 0.084007091 | P5: =K5*$G$7 + L5*$H$7 + M5*$I$7 -> 0.03655
A6: 1998 | B6: 0.16816404 | C6: 0.28337953 | D6: 0.14921432 | F6: Retorno Esperado (premissa) | G6: 0.12 | H6: 0.07 | I6: 0.04 | K6: 0 | L6: 0.15 | M6: =1-K6-L6 -> 0.85 | N6: =SUM(K6:M6) -> 1 | O6: =SQRT(K6^2*$G$4^2 + L6^2*$H$4^2 + M6^2*$I$4^2 + 2*K6*L6*$G$10*$G$4*$H$4 + 2*L6*M6*$G$12*$H$4*$I$4 + 2*K6*M6*$G$11*$G$4*$I$4) -> 0.080490609 | P6: =K6*$G$7 + L6*$H$7 + M6*$I$7 -> 0.037825 | AG6: Taxa Livre de Retorno Anual (EUA): | AI6: 0.043 | AK6: Sharpe: | AL6: =(AL4-AI6)/AK4 -> 0.38568769
A7: 1999 | B7: 0.3862112 | C7: 0.20885351 | D7: -0.082542148 | F7: Retorno - Impostos (15%) | G7: =G6-(0.15*G6) -> 0.102 | H7: =H6-(0.15*H6) -> 0.0595 | I7: =I6-(0.15*I6) -> 0.034 | K7: 0 | L7: 0.2 | M7: =1-K7-L7 -> 0.8 | N7: =SUM(K7:M7) -> 1 | O7: =SQRT(K7^2*$G$4^2 + L7^2*$H$4^2 + M7^2*$I$4^2 + 2*K7*L7*$G$10*$G$4*$H$4 + 2*L7*M7*$G$12*$H$4*$I$4 + 2*K7*M7*$G$11*$G$4*$I$4) -> 0.078344253 | P7: =K7*$G$7 + L7*$H$7 + M7*$I$7 -> 0.0391
A8: 2000 | B8: 0.044529382 | C8: -0.09031819 | D8: 0.16655267 | K8: 0 | L8: 0.25 | M8: =1-K8-L8 -> 0.75 | N8: =SUM(K8:M8) -> 1 | O8: =SQRT(K8^2*$G$4^2 + L8^2*$H$4^2 + M8^2*$I$4^2 + 2*K8*L8*$G$10*$G$4*$H$4 + 2*L8*M8*$G$12*$H$4*$I$4 + 2*K8*M8*$G$11*$G$4*$I$4) -> 0.077681676 | P8: =K8*$G$7 + L8*$H$7 + M8*$I$7 -> 0.040375
A9: 2001 | B9: -0.1135096 | C9: -0.11849759 | D9: 0.055721812 | F9: Pares | G9: Correlação | K9: 0 | L9: 0.3 | M9: =1-K9-L9 -> 0.7 | N9: =SUM(K9:M9) -> 1 | O9: =SQRT(K9^2*$G$4^2 + L9^2*$H$4^2 + M9^2*$I$4^2 + 2*K9*L9*$G$10*$G$4*$H$4 + 2*L9*M9*$G$12*$H$4*$I$4 + 2*K9*M9*$G$11*$G$4*$I$4) -> 0.078540439 | P9: =K9*$G$7 + L9*$H$7 + M9*$I$7 -> 0.04165 | Z9: Alocação de Mínima Variância - Jovem Profissional | AG9: Alocação Ótima Jovem Profissional (Coeficiente de Retorno 0.4)
A10: 2002 | B10: -0.039531947 | C10: -0.21966048 | D10: 0.151164 | F10: Private Equity X S&P500 | G10: =CORREL(Tabela3[Private Equity Returns],Tabela3[S&P500]) -> 0.77043886 | K10: 0 | L10: 0.35 | M10: =1-K10-L10 -> 0.65 | N10: =SUM(K10:M10) -> 1 | O10: =SQRT(K10^2*$G$4^2 + L10^2*$H$4^2 + M10^2*$I$4^2 + 2*K10*L10*$G$10*$G$4*$H$4 + 2*L10*M10*$G$12*$H$4*$I$4 + 2*K10*M10*$G$11*$G$4*$I$4) -> 0.080872092 | P10: =K10*$G$7 + L10*$H$7 + M10*$I$7 -> 0.042925
A11: 2003 | B11: 0.24162203 | C11: 0.283558 | D11: 0.0037531859 | F11: Equity X Treasury Bond | G11: =CORREL(Tabela3[Private Equity Returns],Tabela3[Treasury Bond (10 anos)]) -> -0.13145206 | K11: 0 | L11: 0.4 | M11: =1-K11-L11 -> 0.6 | N11: =SUM(K11:M11) -> 1 | O11: =SQRT(K11^2*$G$4^2 + L11^2*$H$4^2 + M11^2*$I$4^2 + 2*K11*L11*$G$10*$G$4*$H$4 + 2*L11*M11*$G$12*$H$4*$I$4 + 2*K11*M11*$G$11*$G$4*$I$4) -> 0.084554876 | P11: =K11*$G$7 + L11*$H$7 + M11*$I$7 -> 0.0442 | Z11: wPrivate | AA11: wS&P500 | AB11: wTreasury | AC11: Total | AD11: Desvio Padrão do Portifolio | AE11: Retorno Esperado do Portifolio | AG11: wPrivate | AH11: wS&P500 | AI11: wTreasury | AJ11: Total | AK11: Desvio Padrão do Portifolio | AL11: Retorno Esperado do Portifolio
A12: 2004 | B12: 0.28527889 | C12: 0.10742776 | D12: 0.044906837 | F12: S&P500 X Treasury Bond | G12: =CORREL(Tabela3[S&P500],Tabela3[Treasury Bond (10 anos)]) -> -0.16294864 | K12: 0 | L12: 0.45 | M12: =1-K12-L12 -> 0.55 | N12: =SUM(K12:M12) -> 1 | O12: =SQRT(K12^2*$G$4^2 + L12^2*$H$4^2 + M12^2*$I$4^2 + 2*K12*L12*$G$10*$G$4*$H$4 + 2*L12*M12*$G$12*$H$4*$I$4 + 2*K12*M12*$G$11*$G$4*$I$4) -> 0.08942201 | P12: =K12*$G$7 + L12*$H$7 + M12*$I$7 -> 0.045475 | Z12: 0.10580191 | AA12: 0.2 | AB12: 0.69419808 | AC12: =SUM(Z12:AB12) -> 0.99999999 | AD12: =SQRT(Z12^2*$G$4^2 + AA12^2*$H$4^2 + AB12^2*$I$4^2 + 2*Z12*AA12*$G$10*$G$4*$H$4 + 2*AA12*AB12*$G$12*$H$4*$I$4 + 2*Z12*AB12*$G$11*$G$4*$I$4) -> 0.075719976 | AE12: =Z12*$G$7 + AA12*$H$7 + AB12*$I$7 -> 0.04629453 | AG12: =(AG4-Z12)*$AJ$14 + Z12 -> 0.46245655 | AH12: =(AH4-AA12)*$AJ$14 + AA12 -> 0.12 | AI12: =(AI4-AB12)*$AJ$14 + AB12 -> 0.41754344 | AJ12: =SUM(AG12:AI12) -> 1 | AK12: =SQRT(AG12^2*$G$4^2 + AH12^2*$H$4^2 + AI12^2*$I$4^2 + 2*AG12*AH12*$G$10*$G$4*$H$4 + 2*AH12*AI12*$G$12*$H$4*$I$4 + 2*AG12*AI12*$G$11*$G$4*$I$4) -> 0.091628271 | AL12: =AG12*$G$7 + AH12*$H$7 + AI12*$I$7 -> 0.068507045
A13: 2005 | B13: 0.26575343 | C13: 0.048344775 | D13: 0.02867533 | K13: 0 | L13: 0.5 | M13: =1-K13-L13 -> 0.5 | N13: =SUM(K13:M13) -> 1 | O13: =SQRT(K13^2*$G$4^2 + L13^2*$H$4^2 + M13^2*$I$4^2 + 2*K13*L13*$G$10*$G$4*$H$4 + 2*L13*M13*$G$12*$H$4*$I$4 + 2*K13*M13*$G$11*$G$4*$I$4) -> 0.095292191 | P13: =K13*$G$7 + L13*$H$7 + M13*$I$7 -> 0.04675 | Z13: Gastos Anuais: | AB13: 0.02
A14: 2006 | B14: 0.37906171 | C14: 0.15612558 | D14: 0.019610012 | K14: 0 | L14: 0.55 | M14: =1-K14-L14 -> 0.45 | N14: =SUM(K14:M14) -> 1 | O14: =SQRT(K14^2*$G$4^2 + L14^2*$H$4^2 + M14^2*$I$4^2 + 2*K14*L14*$G$10*$G$4*$H$4 + 2*L14*M14*$G$12*$H$4*$I$4 + 2*K14*M14*$G$11*$G$4*$I$4) -> 0.10199237 | P14: =K14*$G$7 + L14*$H$7 + M14*$I$7 -> 0.048025 | Z14: Inflação: | AB14: 0.02 | AD14: Retorno Ajustado com Gastos: | AE14: =AE12-AB13 -> 0.02629453 | AG14: Coeficiente Mínima Variância - Aplicação Ótima: | AJ14: 0.4
A15: 2007 | B15: 0.25253221 | C15: 0.054847352 | D15: 0.10209922 | F15: Utilizamos a seguinte fórmula para obter o Desvio Padrão de um portifólio com as 3 classes: | K15: 0 | L15: 0.6 | M15: =1-K15-L15 -> 0.4 | N15: =SUM(K15:M15) -> 1 | O15: =SQRT(K15^2*$G$4^2 + L15^2*$H$4^2 + M15^2*$I$4^2 + 2*K15*L15*$G$10*$G$4*$H$4 + 2*L15*M15*$G$12*$H$4*$I$4 + 2*K15*M15*$G$11*$G$4*$I$4) -> 0.10937012 | P15: =K15*$G$7 + L15*$H$7 + M15*$I$7 -> 0.0493 | Z15: Expectativa de Vida: | AB15: =60 -> 60 | AG15: 0 = Portifólio de Mínima Variância
A16: 2008 | B16: -0.28966923 | C16: -0.36552344 | D16: 0.2010128 | K16: 0 | L16: 0.65 | M16: =1-K16-L16 -> 0.35 | N16: =SUM(K16:M16) -> 1 | O16: =SQRT(K16^2*$G$4^2 + L16^2*$H$4^2 + M16^2*$I$4^2 + 2*K16*L16*$G$10*$G$4*$H$4 + 2*L16*M16*$G$12*$H$4*$I$4 + 2*K16*M16*$G$11*$G$4*$I$4) -> 0.11729766 | P16: =K16*$G$7 + L16*$H$7 + M16*$I$7 -> 0.050575 | Z16: % Mínimo em Renda Variável: | AB16: 0.2 | AG16: 1 = Aplicação Ótima
A17: 2009 | B17: 0.17127188 | C17: 0.25935234 | D17: -0.11116695 | K17: 0 | L17: 0.7 | M17: =1-K17-L17 -> 0.3 | N17: =SUM(K17:M17) -> 1 | O17: =SQRT(K17^2*$G$4^2 + L17^2*$H$4^2 + M17^2*$I$4^2 + 2*K17*L17*$G$10*$G$4*$H$4 + 2*L17*M17*$G$12*$H$4*$I$4 + 2*K17*M17*$G$11*$G$4*$I$4) -> 0.12567098 | P17: =K17*$G$7 + L17*$H$7 + M17*$I$7 -> 0.05185 | Z17: Retorno Target (Inflação acumulada + 1%): | AB17: =AB14 +(1.01)^(1/(AB15)) - 1 -> 0.020165853
A18: 2010 | B18: 0.20782132 | C18: 0.14821092 | D18: 0.084629339 | K18: 0 | L18: 0.75 | M18: =1-K18-L18 -> 0.25 | N18: =SUM(K18:M18) -> 1 | O18: =SQRT(K18^2*$G$4^2 + L18^2*$H$4^2 + M18^2*$I$4^2 + 2*K18*L18*$G$10*$G$4*$H$4 + 2*L18*M18*$G$12*$H$4*$I$4 + 2*K18*M18*$G$11*$G$4*$I$4) -> 0.13440679 | P18: =K18*$G$7 + L18*$H$7 + M18*$I$7 -> 0.053125
A19: 2011 | B19: 0.069234969 | C19: 0.020983747 | D19: 0.16035335 | K19: 0 | L19: 0.8 | M19: =1-K19-L19 -> 0.2 | N19: =SUM(K19:M19) -> 1 | O19: =SQRT(K19^2*$G$4^2 + L19^2*$H$4^2 + M19^2*$I$4^2 + 2*K19*L19*$G$10*$G$4*$H$4 + 2*L19*M19*$G$12*$H$4*$I$4 + 2*K19*M19*$G$11*$G$4*$I$4) -> 0.14343888 | P19: =K19*$G$7 + L19*$H$7 + M19*$I$7 -> 0.0544
A20: 2012 | B20: 0.14355029 | C20: 0.15890585 | D20: 0.02971572 | K20: 0 | L20: 0.85 | M20: =1-K20-L20 -> 0.15 | N20: =SUM(K20:M20) -> 1 | O20: =SQRT(K20^2*$G$4^2 + L20^2*$H$4^2 + M20^2*$I$4^2 + 2*K20*L20*$G$10*$G$4*$H$4 + 2*L20*M20*$G$12*$H$4*$I$4 + 2*K20*M20*$G$11*$G$4*$I$4) -> 0.15271469 | P20: =K20*$G$7 + L20*$H$7 + M20*$I$7 -> 0.055675 | Z20: Alocação de Mínima Variância - Família em Crescimento | AG20: Alocação Ótima Familia em Crescimento (Coeficiente de Retorno 0.05)
A21: 2013 | B21: 0.20681101 | C21: 0.32145086 | D21: -0.091045688 | K21: 0 | L21: 0.9 | M21: =1-K21-L21 -> 0.1 | N21: =SUM(K21:M21) -> 1 | O21: =SQRT(K21^2*$G$4^2 + L21^2*$H$4^2 + M21^2*$I$4^2 + 2*K21*L21*$G$10*$G$4*$H$4 + 2*L21*M21*$G$12*$H$4*$I$4 + 2*K21*M21*$G$11*$G$4*$I$4) -> 0.16219241 | P21: =K21*$G$7 + L21*$H$7 + M21*$I$7 -> 0.05695
A22: 2014 | B22: 0.10044195 | C22: 0.13524422 | D22: 0.1074618 | K22: 0 | L22: 0.95 | M22: =1-K22-L22 -> 0.05 | N22: =SUM(K22:M22) -> 1 | O22: =SQRT(K22^2*$G$4^2 + L22^2*$H$4^2 + M22^2*$I$4^2 + 2*K22*L22*$G$10*$G$4*$H$4 + 2*L22*M22*$G$12*$H$4*$I$4 + 2*K22*M22*$G$11*$G$4*$I$4) -> 0.17183864 | P22: =K22*$G$7 + L22*$H$7 + M22*$I$7 -> 0.058225 | Z22: wPrivate | AA22: wS&P500 | AB22: wTreasury | AC22: Total | AD22: Desvio Padrão do Portifolio | AE22: Retorno Esperado do Portifolio | AG22: wPrivate | AH22: wS&P500 | AI22: wTreasury | AJ22: Total | AK22: Desvio Padrão do Portifolio | AL22: Retorno Esperado do Portifolio
A23: 2015 | B23: 0.085955738 | C23: 0.013788916 | D23: 0.012842997 | K23: 0 | L23: 1 | M23: =1-K23-L23 -> 0 | N23: =SUM(K23:M23) -> 1 | O23: =SQRT(K23^2*$G$4^2 + L23^2*$H$4^2 + M23^2*$I$4^2 + 2*K23*L23*$G$10*$G$4*$H$4 + 2*L23*M23*$G$12*$H$4*$I$4 + 2*K23*M23*$G$11*$G$4*$I$4) -> 0.18162652 | P23: =K23*$G$7 + L23*$H$7 + M23*$I$7 -> 0.0595 | Z23: 0.3290298 | AA23: 0.15 | AB23: 0.5209702 | AC23: =SUM(Z23:AB23) -> 1 | AD23: =SQRT(Z23^2*$G$4^2 + AA23^2*$H$4^2 + AB23^2*$I$4^2 + 2*Z23*AA23*$G$10*$G$4*$H$4 + 2*AA23*AB23*$G$12*$H$4*$I$4 + 2*Z23*AB23*$G$11*$G$4*$I$4) -> 0.081986642 | AE23: =Z23*$G$7 + AA23*$H$7 + AB23*$I$7 -> 0.060199026 | AG23: =(AG4-Z23)*$AJ$25 + Z23 -> 0.36245024 | AH23: =(AH4-AA23)*$AJ$25 + AA23 -> 0.1425 | AI23: =(AI4-AB23)*$AJ$25 + AB23 -> 0.49504976 | AJ23: =SUM(AG23:AI23) -> 1 | AK23: =SQRT(AG23^2*$G$4^2 + AH23^2*$H$4^2 + AI23^2*$I$4^2 + 2*AG23*AH23*$G$10*$G$4*$H$4 + 2*AH23*AI23*$G$12*$H$4*$I$4 + 2*AG23*AI23*$G$11*$G$4*$I$4) -> 0.084054812 | AL23: =AG23*$G$7 + AH23*$H$7 + AI23*$I$7 -> 0.062280366
A24: 2016 | B24: 0.11346904 | C24: 0.11773081 | D24: 0.0069055047 | F24: Matriz de Correlação | G24: Private Equity | H24: S&P500 | I24: Treasury Bond | K24: 0.05 | L24: {=_xlfn.SEQUENCE(20,,0,5%)} -> 0 | M24: =1-K24-L24 -> 0.95 | N24: =SUM(K24:M24) -> 1 | O24: =SQRT(K24^2*$G$4^2 + L24^2*$H$4^2 + M24^2*$I$4^2 + 2*K24*L24*$G$10*$G$4*$H$4 + 2*L24*M24*$G$12*$H$4*$I$4 + 2*K24*M24*$G$11*$G$4*$I$4) -> 0.08907513 | P24: =K24*$G$7 + L24*$H$7 + M24*$I$7 -> 0.0374 | Z24: Gastos Anuais: | AB24: 0.04
A25: 2017 | B25: 0.22423202 | C25: 0.21605481 | D25: 0.028017163 | F25: Private Equity | G25: =G4 -> 0.15294529 | H25: =G10 -> 0.77043886 | I25: =G11 -> -0.13145206 | K25: 0.05 | L25: 0.05 | M25: =1-K25-L25 -> 0.9 | N25: =SUM(K25:M25) -> 1 | O25: =SQRT(K25^2*$G$4^2 + L25^2*$H$4^2 + M25^2*$I$4^2 + 2*K25*L25*$G$10*$G$4*$H$4 + 2*L25*M25*$G$12*$H$4*$I$4 + 2*K25*M25*$G$11*$G$4*$I$4) -> 0.083999844 | P25: =K25*$G$7 + L25*$H$7 + M25*$I$7 -> 0.038675 | Z25: Inflação: | AB25: 0.02 | AD25: Retorno Ajustado com Gastos: | AE25: =AE23-AB24 -> 0.020199026 | AG25: Coeficiente Mínima Variância - Aplicação Ótima: | AJ25: 0.05
A26: 2018 | B26: 0.093120837 | C26: -0.042268693 | D26: -0.00016692386 | F26: S&P500 | G26: =G10 -> 0.77043886 | H26: =H4 -> 0.18162652 | I26: =G12 -> -0.16294864 | K26: 0.05 | L26: 0.1 | M26: =1-K26-L26 -> 0.85 | N26: =SUM(K26:M26) -> 1 | O26: =SQRT(K26^2*$G$4^2 + L26^2*$H$4^2 + M26^2*$I$4^2 + 2*K26*L26*$G$10*$G$4*$H$4 + 2*L26*M26*$G$12*$H$4*$I$4 + 2*K26*M26*$G$11*$G$4*$I$4) -> 0.080094356 | P26: =K26*$G$7 + L26*$H$7 + M26*$I$7 -> 0.03995 | Z26: Expectativa de Vida: | AB26: =50 -> 50 | AG26: 0 = Portifólio de Mínima Variância
A27: 2019 | B27: 0.17272263 | C27: 0.3121168 | D27: 0.096356307 | F27: Treasury Bond | G27: =G11 -> -0.13145206 | H27: =G12 -> -0.16294864 | I27: =I4 -> 0.094481262 | K27: 0.05 | L27: 0.15 | M27: =1-K27-L27 -> 0.8 | N27: =SUM(K27:M27) -> 1 | O27: =SQRT(K27^2*$G$4^2 + L27^2*$H$4^2 + M27^2*$I$4^2 + 2*K27*L27*$G$10*$G$4*$H$4 + 2*L27*M27*$G$12*$H$4*$I$4 + 2*K27*M27*$G$11*$G$4*$I$4) -> 0.077535637 | P27: =K27*$G$7 + L27*$H$7 + M27*$I$7 -> 0.041225 | R27: Os pesos ótimos foram determinados com o Solver do Excel, minimizando a variância e impondo como restrição que o retorno esperado fosse superior ao retorno-alvo (inflação acumulada + 1%). Para investidores mais jovens, que toleram maior risco em busca de retorno, foi construída uma relação linear entre a carteira de mínima variância e o portfólio de retorno máximo (100% em ilíquidos). Embora os dados históricos indiquem baixa volatilidade e alto retorno nos ativos ilíquidos, essa concentração seria inviável e arriscada no contexto do case, já que esses recursos permanecem travados por sete anos e os gastos devem ser cobertos pelos ativos líquidos. Assim, foram definidos limites de participação de ilíquidos conforme a idade, mantendo a progressão linear de maior exposição para perfis mais jovens, mas dentro de patamares realistas de liquidez e risco. | Z27: % Mínimo em Renda Variável: | AB27: 0.15 | AG27: 1 = Aplicação Ótimca
A28: 2020 | B28: 0.2294 | C28: 0.18023202 | D28: 0.11331898 | K28: 0.05 | L28: 0.2 | M28: =1-K28-L28 -> 0.75 | N28: =SUM(K28:M28) -> 1 | O28: =SQRT(K28^2*$G$4^2 + L28^2*$H$4^2 + M28^2*$I$4^2 + 2*K28*L28*$G$10*$G$4*$H$4 + 2*L28*M28*$G$12*$H$4*$I$4 + 2*K28*M28*$G$11*$G$4*$I$4) -> 0.076459016 | P28: =K28*$G$7 + L28*$H$7 + M28*$I$7 -> 0.0425 | Z28: Retorno Target (Inflação acumulada + 1%): | AB28: =AB25 +(1.01)^(1/(AB26)) - 1 -> 0.020199026
A29: 2021 | B29: 0.0923 | C29: 0.28468852 | D29: -0.044160344 | K29: 0.05 | L29: 0.25 | M29: =1-K29-L29 -> 0.7 | N29: =SUM(K29:M29) -> 1 | O29: =SQRT(K29^2*$G$4^2 + L29^2*$H$4^2 + M29^2*$I$4^2 + 2*K29*L29*$G$10*$G$4*$H$4 + 2*L29*M29*$G$12*$H$4*$I$4 + 2*K29*M29*$G$11*$G$4*$I$4) -> 0.076926746 | P29: =K29*$G$7 + L29*$H$7 + M29*$I$7 -> 0.043775
A30: 2022 | B30: -0.1596 | C30: -0.18037506 | D30: -0.17828172 | K30: 0.05 | L30: 0.3 | M30: =1-K30-L30 -> 0.65 | N30: =SUM(K30:M30) -> 1 | O30: =SQRT(K30^2*$G$4^2 + L30^2*$H$4^2 + M30^2*$I$4^2 + 2*K30*L30*$G$10*$G$4*$H$4 + 2*L30*M30*$G$12*$H$4*$I$4 + 2*K30*M30*$G$11*$G$4*$I$4) -> 0.07891137 | P30: =K30*$G$7 + L30*$H$7 + M30*$I$7 -> 0.04505
A31: 2023 | B31: 0.3021 | C31: 0.26060685 | D31: 0.0388 | K31: 0.05 | L31: 0.35 | M31: =1-K31-L31 -> 0.6 | N31: =SUM(K31:M31) -> 1 | O31: =SQRT(K31^2*$G$4^2 + L31^2*$H$4^2 + M31^2*$I$4^2 + 2*K31*L31*$G$10*$G$4*$H$4 + 2*L31*M31*$G$12*$H$4*$I$4 + 2*K31*M31*$G$11*$G$4*$I$4) -> 0.082303228 | P31: =K31*$G$7 + L31*$H$7 + M31*$I$7 -> 0.046325 | Z31: Alocação Ótima Aposentadoria (Mínima Variância)
A32: 2024 | B32: 0.147 | C32: 0.24878611 | D32: -0.016371801 | K32: 0.05 | L32: 0.4 | M32: =1-K32-L32 -> 0.55 | N32: =SUM(K32:M32) -> 1 | O32: =SQRT(K32^2*$G$4^2 + L32^2*$H$4^2 + M32^2*$I$4^2 + 2*K32*L32*$G$10*$G$4*$H$4 + 2*L32*M32*$G$12*$H$4*$I$4 + 2*K32*M32*$G$11*$G$4*$I$4) -> 0.086937768 | P32: =K32*$G$7 + L32*$H$7 + M32*$I$7 -> 0.0476
A33: fonte: dados providenciados pelos organizadores | K33: 0.05 | L33: 0.45 | M33: =1-K33-L33 -> 0.5 | N33: =SUM(K33:M33) -> 1 | O33: =SQRT(K33^2*$G$4^2 + L33^2*$H$4^2 + M33^2*$I$4^2 + 2*K33*L33*$G$10*$G$4*$H$4 + 2*L33*M33*$G$12*$H$4*$I$4 + 2*K33*M33*$G$11*$G$4*$I$4) -> 0.092628648 | P33: =K33*$G$7 + L33*$H$7 + M33*$I$7 -> 0.048875 | Z33: wPrivate | AA33: wS&P500 | AB33: wTreasury | AC33: Total | AD33: Desvio Padrão do Portifolio | AE33: Retorno Esperado do Portifolio
K34: 0.05 | L34: 0.5 | M34: =1-K34-L34 -> 0.45 | N34: =SUM(K34:M34) -> 1 | O34: =SQRT(K34^2*$G$4^2 + L34^2*$H$4^2 + M34^2*$I$4^2 + 2*K34*L34*$G$10*$G$4*$H$4 + 2*L34*M34*$G$12*$H$4*$I$4 + 2*K34*M34*$G$11*$G$4*$I$4) -> 0.099194226 | P34: =K34*$G$7 + L34*$H$7 + M34*$I$7 -> 0.05015 | Z34: 0.52042067 | AA34: 0.05 | AB34: 0.42957833 | AC34: =SUM(Z34:AB34) -> 0.999999 | AD34: =SQRT(Z34^2*$G$4^2 + AA34^2*$H$4^2 + AB34^2*$I$4^2 + 2*Z34*AA34*$G$10*$G$4*$H$4 + 2*AA34*AB34*$G$12*$H$4*$I$4 + 2*Z34*AB34*$G$11*$G$4*$I$4) -> 0.090607073 | AE34: =Z34*$G$7 + AA34*$H$7 + AB34*$I$7 -> 0.070663572
K35: 0.05 | L35: 0.55 | M35: =1-K35-L35 -> 0.4 | N35: =SUM(K35:M35) -> 1 | O35: =SQRT(K35^2*$G$4^2 + L35^2*$H$4^2 + M35^2*$I$4^2 + 2*K35*L35*$G$10*$G$4*$H$4 + 2*L35*M35*$G$12*$H$4*$I$4 + 2*K35*M35*$G$11*$G$4*$I$4) -> 0.10647281 | P35: =K35*$G$7 + L35*$H$7 + M35*$I$7 -> 0.051425
K36: 0.05 | L36: 0.6 | M36: =1-K36-L36 -> 0.35 | N36: =SUM(K36:M36) -> 1 | O36: =SQRT(K36^2*$G$4^2 + L36^2*$H$4^2 + M36^2*$I$4^2 + 2*K36*L36*$G$10*$G$4*$H$4 + 2*L36*M36*$G$12*$H$4*$I$4 + 2*K36*M36*$G$11*$G$4*$I$4) -> 0.11432831 | P36: =K36*$G$7 + L36*$H$7 + M36*$I$7 -> 0.0527 | Z36: Gastos Anuais: | AB36: 0.05
K37: 0.05 | L37: 0.65 | M37: =1-K37-L37 -> 0.3 | N37: =SUM(K37:M37) -> 1 | O37: =SQRT(K37^2*$G$4^2 + L37^2*$H$4^2 + M37^2*$I$4^2 + 2*K37*L37*$G$10*$G$4*$H$4 + 2*L37*M37*$G$12*$H$4*$I$4 + 2*K37*M37*$G$11*$G$4*$I$4) -> 0.12264991 | P37: =K37*$G$7 + L37*$H$7 + M37*$I$7 -> 0.053975 | Z37: Inflação: | AB37: 0.02 | AD37: Retorno Ajustado com Gastos: | AE37: =AE34-AB36 -> 0.020663572
K38: 0.05 | L38: 0.7 | M38: =1-K38-L38 -> 0.25 | N38: =SUM(K38:M38) -> 1 | O38: =SQRT(K38^2*$G$4^2 + L38^2*$H$4^2 + M38^2*$I$4^2 + 2*K38*L38*$G$10*$G$4*$H$4 + 2*L38*M38*$G$12*$H$4*$I$4 + 2*K38*M38*$G$11*$G$4*$I$4) -> 0.13134906 | P38: =K38*$G$7 + L38*$H$7 + M38*$I$7 -> 0.05525 | Z38: Expectativa de Vida: | AB38: =15 -> 15
K39: 0.05 | L39: 0.75 | M39: =1-K39-L39 -> 0.2 | N39: =SUM(K39:M39) -> 1 | O39: =SQRT(K39^2*$G$4^2 + L39^2*$H$4^2 + M39^2*$I$4^2 + 2*K39*L39*$G$10*$G$4*$H$4 + 2*L39*M39*$G$12*$H$4*$I$4 + 2*K39*M39*$G$11*$G$4*$I$4) -> 0.14035558 | P39: =K39*$G$7 + L39*$H$7 + M39*$I$7 -> 0.056525
K40: 0.05 | L40: 0.8 | M40: =1-K40-L40 -> 0.15 | N40: =SUM(K40:M40) -> 1 | O40: =SQRT(K40^2*$G$4^2 + L40^2*$H$4^2 + M40^2*$I$4^2 + 2*K40*L40*$G$10*$G$4*$H$4 + 2*L40*M40*$G$12*$H$4*$I$4 + 2*K40*M40*$G$11*$G$4*$I$4) -> 0.14961397 | P40: =K40*$G$7 + L40*$H$7 + M40*$I$7 -> 0.0578 | Z40: % Mínimo em Renda Variável: | AB40: 0.05
K41: 0.05 | L41: 0.85 | M41: =1-K41-L41 -> 0.1 | N41: =SUM(K41:M41) -> 1 | O41: =SQRT(K41^2*$G$4^2 + L41^2*$H$4^2 + M41^2*$I$4^2 + 2*K41*L41*$G$10*$G$4*$H$4 + 2*L41*M41*$G$12*$H$4*$I$4 + 2*K41*M41*$G$11*$G$4*$I$4) -> 0.15908025 | P41: =K41*$G$7 + L41*$H$7 + M41*$I$7 -> 0.059075 | Z41: Retorno Target (Inflação acumulada + 1%): | AB41: =AB37 +(1.01)^(1/(AB38)) - 1 -> 0.020663575
K42: 0.05 | L42: 0.9 | M42: =1-K42-L42 -> 0.05 | N42: =SUM(K42:M42) -> 1 | O42: =SQRT(K42^2*$G$4^2 + L42^2*$H$4^2 + M42^2*$I$4^2 + 2*K42*L42*$G$10*$G$4*$H$4 + 2*L42*M42*$G$12*$H$4*$I$4 + 2*K42*M42*$G$11*$G$4*$I$4) -> 0.16871944 | P42: =K42*$G$7 + L42*$H$7 + M42*$I$7 -> 0.06035
K43: 0.05 | L43: 0.95 | M43: =1-K43-L43 -> 0 | N43: =SUM(K43:M43) -> 1 | O43: =SQRT(K43^2*$G$4^2 + L43^2*$H$4^2 + M43^2*$I$4^2 + 2*K43*L43*$G$10*$G$4*$H$4 + 2*L43*M43*$G$12*$H$4*$I$4 + 2*K43*M43*$G$11*$G$4*$I$4) -> 0.17850353 | P43: =K43*$G$7 + L43*$H$7 + M43*$I$7 -> 0.061625
K44: 0.1 | L44: {=_xlfn.SEQUENCE(19,,0,5%)} -> 0 | M44: =1-K44-L44 -> 0.9 | N44: =SUM(K44:M44) -> 1 | O44: =SQRT(K44^2*$G$4^2 + L44^2*$H$4^2 + M44^2*$I$4^2 + 2*K44*L44*$G$10*$G$4*$H$4 + 2*L44*M44*$G$12*$H$4*$I$4 + 2*K44*M44*$G$11*$G$4*$I$4) -> 0.084395728 | P44: =K44*$G$7 + L44*$H$7 + M44*$I$7 -> 0.0408
K45: 0.1 | L45: 0.05 | M45: =1-K45-L45 -> 0.85 | N45: =SUM(K45:M45) -> 1 | O45: =SQRT(K45^2*$G$4^2 + L45^2*$H$4^2 + M45^2*$I$4^2 + 2*K45*L45*$G$10*$G$4*$H$4 + 2*L45*M45*$G$12*$H$4*$I$4 + 2*K45*M45*$G$11*$G$4*$I$4) -> 0.080120886 | P45: =K45*$G$7 + L45*$H$7 + M45*$I$7 -> 0.042075
K46: 0.1 | L46: 0.1 | M46: =1-K46-L46 -> 0.8 | N46: =SUM(K46:M46) -> 1 | O46: =SQRT(K46^2*$G$4^2 + L46^2*$H$4^2 + M46^2*$I$4^2 + 2*K46*L46*$G$10*$G$4*$H$4 + 2*L46*M46*$G$12*$H$4*$I$4 + 2*K46*M46*$G$11*$G$4*$I$4) -> 0.077159645 | P46: =K46*$G$7 + L46*$H$7 + M46*$I$7 -> 0.04335
K47: 0.1 | L47: 0.15 | M47: =1-K47-L47 -> 0.75 | N47: =SUM(K47:M47) -> 1 | O47: =SQRT(K47^2*$G$4^2 + L47^2*$H$4^2 + M47^2*$I$4^2 + 2*K47*L47*$G$10*$G$4*$H$4 + 2*L47*M47*$G$12*$H$4*$I$4 + 2*K47*M47*$G$11*$G$4*$I$4) -> 0.075666387 | P47: =K47*$G$7 + L47*$H$7 + M47*$I$7 -> 0.044625
K48: 0.1 | L48: 0.2 | M48: =1-K48-L48 -> 0.7 | N48: =SUM(K48:M48) -> 1 | O48: =SQRT(K48^2*$G$4^2 + L48^2*$H$4^2 + M48^2*$I$4^2 + 2*K48*L48*$G$10*$G$4*$H$4 + 2*L48*M48*$G$12*$H$4*$I$4 + 2*K48*M48*$G$11*$G$4*$I$4) -> 0.075728004 | P48: =K48*$G$7 + L48*$H$7 + M48*$I$7 -> 0.0459
K49: 0.1 | L49: 0.25 | M49: =1-K49-L49 -> 0.65 | N49: =SUM(K49:M49) -> 1 | O49: =SQRT(K49^2*$G$4^2 + L49^2*$H$4^2 + M49^2*$I$4^2 + 2*K49*L49*$G$10*$G$4*$H$4 + 2*L49*M49*$G$12*$H$4*$I$4 + 2*K49*M49*$G$11*$G$4*$I$4) -> 0.077340778 | P49: =K49*$G$7 + L49*$H$7 + M49*$I$7 -> 0.047175
K50: 0.1 | L50: 0.3 | M50: =1-K50-L50 -> 0.6 | N50: =SUM(K50:M50) -> 1 | O50: =SQRT(K50^2*$G$4^2 + L50^2*$H$4^2 + M50^2*$I$4^2 + 2*K50*L50*$G$10*$G$4*$H$4 + 2*L50*M50*$G$12*$H$4*$I$4 + 2*K50*M50*$G$11*$G$4*$I$4) -> 0.080411432 | P50: =K50*$G$7 + L50*$H$7 + M50*$I$7 -> 0.04845
K51: 0.1 | L51: 0.35 | M51: =1-K51-L51 -> 0.55 | N51: =SUM(K51:M51) -> 1 | O51: =SQRT(K51^2*$G$4^2 + L51^2*$H$4^2 + M51^2*$I$4^2 + 2*K51*L51*$G$10*$G$4*$H$4 + 2*L51*M51*$G$12*$H$4*$I$4 + 2*K51*M51*$G$11*$G$4*$I$4) -> 0.084781706 | P51: =K51*$G$7 + L51*$H$7 + M51*$I$7 -> 0.049725
K52: 0.1 | L52: 0.4 | M52: =1-K52-L52 -> 0.5 | N52: =SUM(K52:M52) -> 1 | O52: =SQRT(K52^2*$G$4^2 + L52^2*$H$4^2 + M52^2*$I$4^2 + 2*K52*L52*$G$10*$G$4*$H$4 + 2*L52*M52*$G$12*$H$4*$I$4 + 2*K52*M52*$G$11*$G$4*$I$4) -> 0.090263027 | P52: =K52*$G$7 + L52*$H$7 + M52*$I$7 -> 0.051
K53: 0.1 | L53: 0.45 | M53: =1-K53-L53 -> 0.45 | N53: =SUM(K53:M53) -> 1 | O53: =SQRT(K53^2*$G$4^2 + L53^2*$H$4^2 + M53^2*$I$4^2 + 2*K53*L53*$G$10*$G$4*$H$4 + 2*L53*M53*$G$12*$H$4*$I$4 + 2*K53*M53*$G$11*$G$4*$I$4) -> 0.096666579 | P53: =K53*$G$7 + L53*$H$7 + M53*$I$7 -> 0.052275
K54: 0.1 | L54: 0.5 | M54: =1-K54-L54 -> 0.4 | N54: =SUM(K54:M54) -> 1 | O54: =SQRT(K54^2*$G$4^2 + L54^2*$H$4^2 + M54^2*$I$4^2 + 2*K54*L54*$G$10*$G$4*$H$4 + 2*L54*M54*$G$12*$H$4*$I$4 + 2*K54*M54*$G$11*$G$4*$I$4) -> 0.10382186 | P54: =K54*$G$7 + L54*$H$7 + M54*$I$7 -> 0.05355
K55: 0.1 | L55: 0.55 | M55: =1-K55-L55 -> 0.35 | N55: =SUM(K55:M55) -> 1 | O55: =SQRT(K55^2*$G$4^2 + L55^2*$H$4^2 + M55^2*$I$4^2 + 2*K55*L55*$G$10*$G$4*$H$4 + 2*L55*M55*$G$12*$H$4*$I$4 + 2*K55*M55*$G$11*$G$4*$I$4) -> 0.11158434 | P55: =K55*$G$7 + L55*$H$7 + M55*$I$7 -> 0.054825
K56: 0.1 | L56: 0.6 | M56: =1-K56-L56 -> 0.3 | N56: =SUM(K56:M56) -> 1 | O56: =SQRT(K56^2*$G$4^2 + L56^2*$H$4^2 + M56^2*$I$4^2 + 2*K56*L56*$G$10*$G$4*$H$4 + 2*L56*M56*$G$12*$H$4*$I$4 + 2*K56*M56*$G$11*$G$4*$I$4) -> 0.11983609 | P56: =K56*$G$7 + L56*$H$7 + M56*$I$7 -> 0.0561
... K62: 0.1 | L62: 0.9 | M62: =1-K62-L62 -> 0 | N62: =SUM(K62:M62) -> 1 | O62: =SQRT(K62^2*$G$4^2 + L62^2*$H$4^2 + M62^2*$I$4^2 + 2*K62*L62*$G$10*$G$4*$H$4 + 2*L62*M62*$G$12*$H$4*$I$4 + 2*K62*M62*$G$11*$G$4*$I$4) -> 0.17551841 | P62: =K62*$G$7 + L62*$H$7 + M62*$I$7 -> 0.06375
K63: 0.15 | L63: {=_xlfn.SEQUENCE(18,,0,5%)} -> 0 | M63: =1-K63-L63 -> 0.85 | N63: =SUM(K63:M63) -> 1 | O63: =SQRT(K63^2*$G$4^2 + L63^2*$H$4^2 + M63^2*$I$4^2 + 2*K63*L63*$G$10*$G$4*$H$4 + 2*L63*M63*$G$12*$H$4*$I$4 + 2*K63*M63*$G$11*$G$4*$I$4) -> 0.08056978 | P63: =K63*$G$7 + L63*$H$7 + M63*$I$7 -> 0.0442
K64: 0.15 | L64: 0.05 | M64: =1-K64-L64 -> 0.8 | N64: =SUM(K64:M64) -> 1 | O64: =SQRT(K64^2*$G$4^2 + L64^2*$H$4^2 + M64^2*$I$4^2 + 2*K64*L64*$G$10*$G$4*$H$4 + 2*L64*M64*$G$12*$H$4*$I$4 + 2*K64*M64*$G$11*$G$4*$I$4) -> 0.077222595 | P64: =K64*$G$7 + L64*$H$7 + M64*$I$7 -> 0.045475
K65: 0.15 | L65: 0.1 | M65: =1-K65-L65 -> 0.75 | N65: =SUM(K65:M65) -> 1 | O65: =SQRT(K65^2*$G$4^2 + L65^2*$H$4^2 + M65^2*$I$4^2 + 2*K65*L65*$G$10*$G$4*$H$4 + 2*L65*M65*$G$12*$H$4*$I$4 + 2*K65*M65*$G$11*$G$4*$I$4) -> 0.075317368 | P65: =K65*$G$7 + L65*$H$7 + M65*$I$7 -> 0.04675
K66: 0.15 | L66: 0.15 | M66: =1-K66-L66 -> 0.7 | N66: =SUM(K66:M66) -> 1 | O66: =SQRT(K66^2*$G$4^2 + L66^2*$H$4^2 + M66^2*$I$4^2 + 2*K66*L66*$G$10*$G$4*$H$4 + 2*L66*M66*$G$12*$H$4*$I$4 + 2*K66*M66*$G$11*$G$4*$I$4) -> 0.074964122 | P66: =K66*$G$7 + L66*$H$7 + M66*$I$7 -> 0.048025
K67: 0.15 | L67: 0.2 | M67: =1-K67-L67 -> 0.65 | N67: =SUM(K67:M67) -> 1 | O67: =SQRT(K67^2*$G$4^2 + L67^2*$H$4^2 + M67^2*$I$4^2 + 2*K67*L67*$G$10*$G$4*$H$4 + 2*L67*M67*$G$12*$H$4*$I$4 + 2*K67*M67*$G$11*$G$4*$I$4) -> 0.076184449 | P67: =K67*$G$7 + L67*$H$7 + M67*$I$7 -> 0.0493
K68: 0.15 | L68: 0.25 | M68: =1-K68-L68 -> 0.6 | N68: =SUM(K68:M68) -> 1 | O68: =SQRT(K68^2*$G$4^2 + L68^2*$H$4^2 + M68^2*$I$4^2 + 2*K68*L68*$G$10*$G$4*$H$4 + 2*L68*M68*$G$12*$H$4*$I$4 + 2*K68*M68*$G$11*$G$4*$I$4) -> 0.078905374 | P68: =K68*$G$7 + L68*$H$7 + M68*$I$7 -> 0.050575
K69: 0.15 | L69: 0.3 | M69: =1-K69-L69 -> 0.55 | N69: =SUM(K69:M69) -> 1 | O69: =SQRT(K69^2*$G$4^2 + L69^2*$H$4^2 + M69^2*$I$4^2 + 2*K69*L69*$G$10*$G$4*$H$4 + 2*L69*M69*$G$12*$H$4*$I$4 + 2*K69*M69*$G$11*$G$4*$I$4) -> 0.082979411 | P69: =K69*$G$7 + L69*$H$7 + M69*$I$7 -> 0.05185
K70: 0.15 | L70: 0.35 | M70: =1-K70-L70 -> 0.5 | N70: =SUM(K70:M70) -> 1 | O70: =SQRT(K70^2*$G$4^2 + L70^2*$H$4^2 + M70^2*$I$4^2 + 2*K70*L70*$G$10*$G$4*$H$4 + 2*L70*M70*$G$12*$H$4*$I$4 + 2*K70*M70*$G$11*$G$4*$I$4) -> 0.088219297 | P70: =K70*$G$7 + L70*$H$7 + M70*$I$7 -> 0.053125
K71: 0.15 | L71: 0.4 | M71: =1-K71-L71 -> 0.45 | N71: =SUM(K71:M71) -> 1 | O71: =SQRT(K71^2*$G$4^2 + L71^2*$H$4^2 + M71^2*$I$4^2 + 2*K71*L71*$G$10*$G$4*$H$4 + 2*L71*M71*$G$12*$H$4*$I$4 + 2*K71*M71*$G$11*$G$4*$I$4) -> 0.094431155 | P71: =K71*$G$7 + L71*$H$7 + M71*$I$7 -> 0.0544
K72: 0.15 | L72: 0.45 | M72: =1-K72-L72 -> 0.4 | N72: =SUM(K72:M72) -> 1 | O72: =SQRT(K72^2*$G$4^2 + L72^2*$H$4^2 + M72^2*$I$4^2 + 2*K72*L72*$G$10*$G$4*$H$4 + 2*L72*M72*$G$12*$H$4*$I$4 + 2*K72*M72*$G$11*$G$4*$I$4) -> 0.10143657 | P72: =K72*$G$7 + L72*$H$7 + M72*$I$7 -> 0.055675
K73: 0.15 | L73: 0.5 | M73: =1-K73-L73 -> 0.35 | N73: =SUM(K73:M73) -> 1 | O73: =SQRT(K73^2*$G$4^2 + L73^2*$H$4^2 + M73^2*$I$4^2 + 2*K73*L73*$G$10*$G$4*$H$4 + 2*L73*M73*$G$12*$H$4*$I$4 + 2*K73*M73*$G$11*$G$4*$I$4) -> 0.10908277 | P73: =K73*$G$7 + L73*$H$7 + M73*$I$7 -> 0.05695
K74: 0.15 | L74: 0.55 | M74: =1-K74-L74 -> 0.3 | N74: =SUM(K74:M74) -> 1 | O74: =SQRT(K74^2*$G$4^2 + L74^2*$H$4^2 + M74^2*$I$4^2 + 2*K74*L74*$G$10*$G$4*$H$4 + 2*L74*M74*$G$12*$H$4*$I$4 + 2*K74*M74*$G$11*$G$4*$I$4) -> 0.11724445 | P74: =K74*$G$7 + L74*$H$7 + M74*$I$7 -> 0.058225
K75: 0.15 | L75: 0.6 | M75: =1-K75-L75 -> 0.25 | N75: =SUM(K75:M75) -> 1 | O75: =SQRT(K75^2*$G$4^2 + L75^2*$H$4^2 + M75^2*$I$4^2 + 2*K75*L75*$G$10*$G$4*$H$4 + 2*L75*M75*$G$12*$H$4*$I$4 + 2*K75*M75*$G$11*$G$4*$I$4) -> 0.12582133 | P75: =K75*$G$7 + L75*$H$7 + M75*$I$7 -> 0.0595
... K80: 0.15 | L80: 0.85 | M80: =1-K80-L80 -> 0 | N80: =SUM(K80:M80) -> 1 | O80: =SQRT(K80^2*$G$4^2 + L80^2*$H$4^2 + M80^2*$I$4^2 + 2*K80*L80*$G$10*$G$4*$H$4 + 2*L80*M80*$G$12*$H$4*$I$4 + 2*K80*M80*$G$11*$G$4*$I$4) -> 0.1726783 | P80: =K80*$G$7 + L80*$H$7 + M80*$I$7 -> 0.065875
K81: 0.2 | L81: {=_xlfn.SEQUENCE(17,,0,5%)} -> 0 | M81: =1-K81-L81 -> 0.8 | N81: =SUM(K81:M81) -> 1 | O81: =SQRT(K81^2*$G$4^2 + L81^2*$H$4^2 + M81^2*$I$4^2 + 2*K81*L81*$G$10*$G$4*$H$4 + 2*L81*M81*$G$12*$H$4*$I$4 + 2*K81*M81*$G$11*$G$4*$I$4) -> 0.077723422 | P81: =K81*$G$7 + L81*$H$7 + M81*$I$7 -> 0.0476
K82: 0.2 | L82: 0.05 | M82: =1-K82-L82 -> 0.75 | N82: =SUM(K82:M82) -> 1 | O82: =SQRT(K82^2*$G$4^2 + L82^2*$H$4^2 + M82^2*$I$4^2 + 2*K82*L82*$G$10*$G$4*$H$4 + 2*L82*M82*$G$12*$H$4*$I$4 + 2*K82*M82*$G$11*$G$4*$I$4) -> 0.075418116 | P82: =K82*$G$7 + L82*$H$7 + M82*$I$7 -> 0.048875
K83: 0.2 | L83: 0.1 | M83: =1-K83-L83 -> 0.7 | N83: =SUM(K83:M83) -> 1 | O83: =SQRT(K83^2*$G$4^2 + L83^2*$H$4^2 + M83^2*$I$4^2 + 2*K83*L83*$G$10*$G$4*$H$4 + 2*L83*M83*$G$12*$H$4*$I$4 + 2*K83*M83*$G$11*$G$4*$I$4) -> 0.074648451 | P83: =K83*$G$7 + L83*$H$7 + M83*$I$7 -> 0.05015
K84: 0.2 | L84: 0.15 | M84: =1-K84-L84 -> 0.65 | N84: =SUM(K84:M84) -> 1 | O84: =SQRT(K84^2*$G$4^2 + L84^2*$H$4^2 + M84^2*$I$4^2 + 2*K84*L84*$G$10*$G$4*$H$4 + 2*L84*M84*$G$12*$H$4*$I$4 + 2*K84*M84*$G$11*$G$4*$I$4) -> 0.075461429 | P84: =K84*$G$7 + L84*$H$7 + M84*$I$7 -> 0.051425
K85: 0.2 | L85: 0.2 | M85: =1-K85-L85 -> 0.6 | N85: =SUM(K85:M85) -> 1 | O85: =SQRT(K85^2*$G$4^2 + L85^2*$H$4^2 + M85^2*$I$4^2 + 2*K85*L85*$G$10*$G$4*$H$4 + 2*L85*M85*$G$12*$H$4*$I$4 + 2*K85*M85*$G$11*$G$4*$I$4) -> 0.077807457 | P85: =K85*$G$7 + L85*$H$7 + M85*$I$7 -> 0.0527
K86: 0.2 | L86: 0.25 | M86: =1-K86-L86 -> 0.55 | N86: =SUM(K86:M86) -> 1 | O86: =SQRT(K86^2*$G$4^2 + L86^2*$H$4^2 + M86^2*$I$4^2 + 2*K86*L86*$G$10*$G$4*$H$4 + 2*L86*M86*$G$12*$H$4*$I$4 + 2*K86*M86*$G$11*$G$4*$I$4) -> 0.08155434 | P86: =K86*$G$7 + L86*$H$7 + M86*$I$7 -> 0.053975
K87: 0.2 | L87: 0.3 | M87: =1-K87-L87 -> 0.5 | N87: =SUM(K87:M87) -> 1 | O87: =SQRT(K87^2*$G$4^2 + L87^2*$H$4^2 + M87^2*$I$4^2 + 2*K87*L87*$G$10*$G$4*$H$4 + 2*L87*M87*$G$12*$H$4*$I$4 + 2*K87*M87*$G$11*$G$4*$I$4) -> 0.086520271 | P87: =K87*$G$7 + L87*$H$7 + M87*$I$7 -> 0.05525
K88: 0.2 | L88: 0.35 | M88: =1-K88-L88 -> 0.45 | N88: =SUM(K88:M88) -> 1 | O88: =SQRT(K88^2*$G$4^2 + L88^2*$H$4^2 + M88^2*$I$4^2 + 2*K88*L88*$G$10*$G$4*$H$4 + 2*L88*M88*$G$12*$H$4*$I$4 + 2*K88*M88*$G$11*$G$4*$I$4) -> 0.092509142 | P88: =K88*$G$7 + L88*$H$7 + M88*$I$7 -> 0.056525
K89: 0.2 | L89: 0.4 | M89: =1-K89-L89 -> 0.4 | N89: =SUM(K89:M89) -> 1 | O89: =SQRT(K89^2*$G$4^2 + L89^2*$H$4^2 + M89^2*$I$4^2 + 2*K89*L89*$G$10*$G$4*$H$4 + 2*L89*M89*$G$12*$H$4*$I$4 + 2*K89*M89*$G$11*$G$4*$I$4) -> 0.099336108 | P89: =K89*$G$7 + L89*$H$7 + M89*$I$7 -> 0.0578
K90: 0.2 | L90: 0.45 | M90: =1-K90-L90 -> 0.35 | N90: =SUM(K90:M90) -> 1 | O90: =SQRT(K90^2*$G$4^2 + L90^2*$H$4^2 + M90^2*$I$4^2 + 2*K90*L90*$G$10*$G$4*$H$4 + 2*L90*M90*$G$12*$H$4*$I$4 + 2*K90*M90*$G$11*$G$4*$I$4) -> 0.10684063 | P90: =K90*$G$7 + L90*$H$7 + M90*$I$7 -> 0.059075
K91: 0.2 | L91: 0.5 | M91: =1-K91-L91 -> 0.3 | N91: =SUM(K91:M91) -> 1 | O91: =SQRT(K91^2*$G$4^2 + L91^2*$H$4^2 + M91^2*$I$4^2 + 2*K91*L91*$G$10*$G$4*$H$4 + 2*L91*M91*$G$12*$H$4*$I$4 + 2*K91*M91*$G$11*$G$4*$I$4) -> 0.11489001 | P91: =K91*$G$7 + L91*$H$7 + M91*$I$7 -> 0.06035
K92: 0.2 | L92: 0.55 | M92: =1-K92-L92 -> 0.25 | N92: =SUM(K92:M92) -> 1 | O92: =SQRT(K92^2*$G$4^2 + L92^2*$H$4^2 + M92^2*$I$4^2 + 2*K92*L92*$G$10*$G$4*$H$4 + 2*L92*M92*$G$12*$H$4*$I$4 + 2*K92*M92*$G$11*$G$4*$I$4) -> 0.12337766 | P92: =K92*$G$7 + L92*$H$7 + M92*$I$7 -> 0.061625
K93: 0.2 | L93: 0.6 | M93: =1-K93-L93 -> 0.2 | N93: =SUM(K93:M93) -> 1 | O93: =SQRT(K93^2*$G$4^2 + L93^2*$H$4^2 + M93^2*$I$4^2 + 2*K93*L93*$G$10*$G$4*$H$4 + 2*L93*M93*$G$12*$H$4*$I$4 + 2*K93*M93*$G$11*$G$4*$I$4) -> 0.1322192 | P93: =K93*$G$7 + L93*$H$7 + M93*$I$7 -> 0.0629
... K97: 0.2 | L97: 0.8 | M97: =1-K97-L97 -> 0 | N97: =SUM(K97:M97) -> 1 | O97: =SQRT(K97^2*$G$4^2 + L97^2*$H$4^2 + M97^2*$I$4^2 + 2*K97*L97*$G$10*$G$4*$H$4 + 2*L97*M97*$G$12*$H$4*$I$4 + 2*K97*M97*$G$11*$G$4*$I$4) -> 0.16999048 | P97: =K97*$G$7 + L97*$H$7 + M97*$I$7 -> 0.068
K98: 0.25 | L98: {=_xlfn.SEQUENCE(16,,0,5%)} -> 0 | M98: =1-K98-L98 -> 0.75 | N98: =SUM(K98:M98) -> 1 | O98: =SQRT(K98^2*$G$4^2 + L98^2*$H$4^2 + M98^2*$I$4^2 + 2*K98*L98*$G$10*$G$4*$H$4 + 2*L98*M98*$G$12*$H$4*$I$4 + 2*K98*M98*$G$11*$G$4*$I$4) -> 0.075966844 | P98: =K98*$G$7 + L98*$H$7 + M98*$I$7 -> 0.051
K99: 0.25 | L99: 0.05 | M99: =1-K99-L99 -> 0.7 | N99: =SUM(K99:M99) -> 1 | O99: =SQRT(K99^2*$G$4^2 + L99^2*$H$4^2 + M99^2*$I$4^2 + 2*K99*L99*$G$10*$G$4*$H$4 + 2*L99*M99*$G$12*$H$4*$I$4 + 2*K99*M99*$G$11*$G$4*$I$4) -> 0.074786668 | P99: =K99*$G$7 + L99*$H$7 + M99*$I$7 -> 0.052275
K100: 0.25 | L100: 0.1 | M100: =1-K100-L100 -> 0.65 | N100: =SUM(K100:M100) -> 1 | O100: =SQRT(K100^2*$G$4^2 + L100^2*$H$4^2 + M100^2*$I$4^2 + 2*K100*L100*$G$10*$G$4*$H$4 + 2*L100*M100*$G$12*$H$4*$I$4 + 2*K100*M100*$G$11*$G$4*$I$4) -> 0.07518422 | P100: =K100*$G$7 + L100*$H$7 + M100*$I$7 -> 0.05355
K101: 0.25 | L101: 0.15 | M101: =1-K101-L101 -> 0.6 | N101: =SUM(K101:M101) -> 1 | O101: =SQRT(K101^2*$G$4^2 + L101^2*$H$4^2 + M101^2*$I$4^2 + 2*K101*L101*$G$10*$G$4*$H$4 + 2*L101*M101*$G$12*$H$4*$I$4 + 2*K101*M101*$G$11*$G$4*$I$4) -> 0.077135111 | P101: =K101*$G$7 + L101*$H$7 + M101*$I$7 -> 0.054825
K102: 0.25 | L102: 0.2 | M102: =1-K102-L102 -> 0.55 | N102: =SUM(K102:M102) -> 1 | O102: =SQRT(K102^2*$G$4^2 + L102^2*$H$4^2 + M102^2*$I$4^2 + 2*K102*L102*$G$10*$G$4*$H$4 + 2*L102*M102*$G$12*$H$4*$I$4 + 2*K102*M102*$G$11*$G$4*$I$4) -> 0.080526521 | P102: =K102*$G$7 + L102*$H$7 + M102*$I$7 -> 0.0561
K103: 0.25 | L103: 0.25 | M103: =1-K103-L103 -> 0.5 | N103: =SUM(K103:M103) -> 1 | O103: =SQRT(K103^2*$G$4^2 + L103^2*$H$4^2 + M103^2*$I$4^2 + 2*K103*L103*$G$10*$G$4*$H$4 + 2*L103*M103*$G$12*$H$4*$I$4 + 2*K103*M103*$G$11*$G$4*$I$4) -> 0.085186577 | P103: =K103*$G$7 + L103*$H$7 + M103*$I$7 -> 0.057375
K104: 0.25 | L104: 0.3 | M104: =1-K104-L104 -> 0.45 | N104: =SUM(K104:M104) -> 1 | O104: =SQRT(K104^2*$G$4^2 + L104^2*$H$4^2 + M104^2*$I$4^2 + 2*K104*L104*$G$10*$G$4*$H$4 + 2*L104*M104*$G$12*$H$4*$I$4 + 2*K104*M104*$G$11*$G$4*$I$4) -> 0.090920417 | P104: =K104*$G$7 + L104*$H$7 + M104*$I$7 -> 0.05865
K105: 0.25 | L105: 0.35 | M105: =1-K105-L105 -> 0.4 | N105: =SUM(K105:M105) -> 1 | O105: =SQRT(K105^2*$G$4^2 + L105^2*$H$4^2 + M105^2*$I$4^2 + 2*K105*L105*$G$10*$G$4*$H$4 + 2*L105*M105*$G$12*$H$4*$I$4 + 2*K105*M105*$G$11*$G$4*$I$4) -> 0.097538857 | P105: =K105*$G$7 + L105*$H$7 + M105*$I$7 -> 0.059925
K106: 0.25 | L106: 0.4 | M106: =1-K106-L106 -> 0.35 | N106: =SUM(K106:M106) -> 1 | O106: =SQRT(K106^2*$G$4^2 + L106^2*$H$4^2 + M106^2*$I$4^2 + 2*K106*L106*$G$10*$G$4*$H$4 + 2*L106*M106*$G$12*$H$4*$I$4 + 2*K106*M106*$G$11*$G$4*$I$4) -> 0.10487455 | P106: =K106*$G$7 + L106*$H$7 + M106*$I$7 -> 0.0612
K107: 0.25 | L107: 0.45 | M107: =1-K107-L107 -> 0.3 | N107: =SUM(K107:M107) -> 1 | O107: =SQRT(K107^2*$G$4^2 + L107^2*$H$4^2 + M107^2*$I$4^2 + 2*K107*L107*$G$10*$G$4*$H$4 + 2*L107*M107*$G$12*$H$4*$I$4 + 2*K107*M107*$G$11*$G$4*$I$4) -> 0.11278764 | P107: =K107*$G$7 + L107*$H$7 + M107*$I$7 -> 0.062475
K108: 0.25 | L108: 0.5 | M108: =1-K108-L108 -> 0.25 | N108: =SUM(K108:M108) -> 1 | O108: =SQRT(K108^2*$G$4^2 + L108^2*$H$4^2 + M108^2*$I$4^2 + 2*K108*L108*$G$10*$G$4*$H$4 + 2*L108*M108*$G$12*$H$4*$I$4 + 2*K108*M108*$G$11*$G$4*$I$4) -> 0.12116505 | P108: =K108*$G$7 + L108*$H$7 + M108*$I$7 -> 0.06375
K109: 0.25 | L109: 0.55 | M109: =1-K109-L109 -> 0.2 | N109: =SUM(K109:M109) -> 1 | O109: =SQRT(K109^2*$G$4^2 + L109^2*$H$4^2 + M109^2*$I$4^2 + 2*K109*L109*$G$10*$G$4*$H$4 + 2*L109*M109*$G$12*$H$4*$I$4 + 2*K109*M109*$G$11*$G$4*$I$4) -> 0.12991699 | P109: =K109*$G$7 + L109*$H$7 + M109*$I$7 -> 0.065025
K110: 0.25 | L110: 0.6 | M110: =1-K110-L110 -> 0.15 | N110: =SUM(K110:M110) -> 1 | O110: =SQRT(K110^2*$G$4^2 + L110^2*$H$4^2 + M110^2*$I$4^2 + 2*K110*L110*$G$10*$G$4*$H$4 + 2*L110*M110*$G$12*$H$4*$I$4 + 2*K110*M110*$G$11*$G$4*$I$4) -> 0.13897271 | P110: =K110*$G$7 + L110*$H$7 + M110*$I$7 -> 0.0663
... K113: 0.25 | L113: 0.75 | M113: =1-K113-L113 -> 0 | N113: =SUM(K113:M113) -> 1 | O113: =SQRT(K113^2*$G$4^2 + L113^2*$H$4^2 + M113^2*$I$4^2 + 2*K113*L113*$G$10*$G$4*$H$4 + 2*L113*M113*$G$12*$H$4*$I$4 + 2*K113*M113*$G$11*$G$4*$I$4) -> 0.16746227 | P113: =K113*$G$7 + L113*$H$7 + M113*$I$7 -> 0.070125
K114: 0.3 | L114: {=_xlfn.SEQUENCE(15,,0,5%)} -> 0 | M114: =1-K114-L114 -> 0.7 | N114: =SUM(K114:M114) -> 1 | O114: =SQRT(K114^2*$G$4^2 + L114^2*$H$4^2 + M114^2*$I$4^2 + 2*K114*L114*$G$10*$G$4*$H$4 + 2*L114*M114*$G$12*$H$4*$I$4 + 2*K114*M114*$G$11*$G$4*$I$4) -> 0.075376274 | P114: =K114*$G$7 + L114*$H$7 + M114*$I$7 -> 0.0544
...

Sheet 2. Calculo de Herança
A1: Variáveis Utilizadas | E1: Valores por Fase da Vida (Obtidos na Primeira Parte) | K1: Resultados
A2: Parâmetro | B2: Valor padrão | C2: Descrição | E2: Fase da Vida | F2: Jovem Profissional | G2: Familia em Crescimento | H2: Aposentadoria
A3: Peso_ILIQ | B3: =HLOOKUP($L$3,Tabela2[#All],4,FALSE) -> 0.52042067 | C3: % alvo do patrimônio em Ilíquidos | E3: Idade Inicial | F3: 30 | G3: 40 | H3: 75 | K3: Fase da Vida: | L3: Aposentadoria | M3: Seleciona aqui a fase da vida
A4: Peso_LIQ | B4: =1 -B3 -> 0.47957933 | C4: % alvo do patrimônio em RV + RF | E4: % Gastos | F4: 0.02 | G4: 0.04 | H4: 0.05
A5: Mix_RV_dentro_LIQ | B5: =HLOOKUP($L$3,Tabela2[#All],6,FALSE) / (HLOOKUP($L$3,Tabela2[#All],6,FALSE) + HLOOKUP($L$3,Tabela2[#All],5,FALSE)) -> 0.10425826 | C5: % inicial de alocação em RV dentro dos ativos Líquidos | E5: % Base de ILIQ | F5: ='1. Dados Históricos'!AG12 -> 0.46245655 | G5: ='1. Dados Históricos'!AG23 -> 0.36245024 | H5: ='1. Dados Históricos'!Z34 -> 0.52042067 | K5: Herança target | L5: {=INDEX($AA:$AA,20+$B$17-$B$18)*(1.01)} -> 27186540
A6: Mix_RF_dentro_LIQ | B6: =1 -B5 -> 0.89574174 | C6: % inicial de alocação em RF /dentro dos ativos Líquidos | E6: % Base de Renda Fixa | F6: ='1. Dados Históricos'!AI12 -> 0.41754344 | G6: ='1. Dados Históricos'!AI23 -> 0.49504976 | H6: ='1. Dados Históricos'!AB34 -> 0.42957833 | K6: Patrimônio Final | L6: {=INDEX($Y:$Y,20+$B$17-$B$18)} -> 30917709
A7: Taxa_RF | B7: 0.04 | C7: Rendimento da Renda Fixa | E7: % Base de Renda Variável | F7: ='1. Dados Históricos'!AH12 -> 0.12 | G7: ='1. Dados Históricos'!AH23 -> 0.1425 | H7: ='1. Dados Históricos'!AA34 -> 0.05 | K7: ITCMD | L7: =$L$6*$B$13 -> 1236708.3
A8: Taxa_RV | B8: 0.07 | C8: Rendimento da Renda variável | E8: % MAX ILIQ | F8: 0.6 | G8: 0.5 | H8: 0.55 | I8: Limites Estabelecidos Empiricamente | K8: Herança (após ITCMD) | L8: =$L$6-$L$7 -> 29681000
A9: Taxa_ILIQ | B9: 0.12 | C9: Rendimento dos ilíquidos
A10: Inflação | B10: 0.02 | C10: Inflação
A11: Gastos% | B11: =HLOOKUP($L$3,Tabela2[#All],3,FALSE) -> 0.05 | C11: % do patrimônio que o cliente gasta anualmente
A12: IR | B12: 0.15 | C12: Imposto sobre o ganho realizado | J12: Coluna1 | K12: Jovem Profissional | L12: Família em Crescimento | M12: Aposentadoria
A13: ITCMD | B13: 0.04 | C13: Imposto sobre a herança | J13: Herança Target | K13: 66276822 | L13: 54370078 | M13: 27186540
A14: Ano_Liquidez | B14: 7 | C14: Ciclo de travamento dos ilíquidos | J14: Patrimônio Final | K14: 5.1074389e+08 | L14: 81555955 | M14: 30917709
A15: Peso_Max_ILIQ | B15: =HLOOKUP($L$3,Tabela2[#All],7,FALSE) -> 0.55 | C15: Acionador para reduzir risco (liquidity-aware) | J15: ITCMD | K15: 20429756 | L15: 3262238.2 | M15: 1236708.3
A16: Patrimônio Inicial | B16: 20000000 | C16: Patrimônio inicial do cliente | J16: Herança | K16: 4.9031414e+08 | L16: 78293717 | M16: 29681000
A17: Expectativa de Vida | B17: 90 | C17: Expectativa de vida do cliente | J17: Maior Drawdown | K17: -0.34 | L17: -0.33 | M17: -0.55
A18: Idade Inicial | B18: =HLOOKUP($L$3,Tabela2[#All],2,FALSE) -> 75 | C18: Idade do cliente no momento de contratação | J18: Retorno no Backtest | K18: 7.2457224 | L18: 2.6884297 | M18: 2.1951272
A20: Ano | B20: Patrimônio Inicial | C20: Patrimônio RF + RV Inicial | D20: Patrimônio ILIQ | E20: % RV + RF | F20: % ILIQ | G20: % RV (dentro de RF + RV) | H20: % RF (dentro de RF + RV) | I20: Patrimônio RV | J20: Patrimônio RF | K20: % Prevista Rebalanceamento RV | L20: % Prevista Rebalanceamento RF | M20: Custo Base RV | N20: Custo Base RF | O20: Lucro Total Latente RV | P20: Lucro Total Latente RF | Q20: Lucro Realizado RV | R20: Lucro Realizado RF | S20: Gastos | T20: Rendimento RV | U20: Rendimento RF | V20: Rendimento ILIQ | W20: Total RF + RV Antes dos Gastos e Impostos | X20: Impostos | Y20: Patrimônio Final | Z20: Inflação Acumulada | AA20: Patrimônio Corrigido pela Inflação
A21: {=_xlfn.SEQUENCE(70,,,1)} -> 1 | B21: =IF($A21=1,$B$16,Y20) -> 20000000 | C21: =IF(OR($A21=1, MOD($A21,7)=1),$B$4*$B21, I20+T20+J20+U20-(S20+X20)) -> 9591586.5 | D21: =IF(OR($A21=1, MOD($A21,7)=1),$B$3*$B21, D20+V20) -> 10408413 | E21: =C21/B21 -> 0.47957933 | F21: =D21/B21 -> 0.52042067 | G21: =MAX(0.05, $B$5 * EXP(-LN(2) * MAX(0, F21 - $B$15) / 0.1)) -> 0.10425826 | H21: =1-G21 -> 0.89574174 | I21: =C21*G21 -> 1000002.1 | J21: =C21*H21 -> 8591584.4 | K21: =- ((I21+T21)/$W21 - MAX(0.05, $B$5 * EXP(-LN(2) * MAX(0, (($D21+$V21)/($B21+$T21+$U21+$V21-$S21)) - $B$15) / 0.1))) -> -0.012444299 | L21: =- ((J21+U21)/$W21 - (1 - MAX(0.05, $B$5 * EXP(-LN(2) * MAX(0, (($D21+$V21)/($B21+$T21+$U21+$V21-$S21)) - $B$15) / 0.1)))) -> 0.012444299 | M21: =IF(OR($A21=1, MOD($A21,7)=1), I21, (M20 * MIN(1, 1+(K21/G21))) + ($C21)*(MAX((K21),0))) - G21*$S21 -> 895743.83 | N21: =IF(OR($A21=1, MOD($A21,7)=1), J21, (N20 * MIN(1, 1+(L21/H21))) + ($C21)*(MAX((L21),0))) - H21*$S21 -> 7695842.7 | O21: =(I21+T21) - M21 - (G21*$S21) -> 70000.146 | P21: =(J21+U21) - N21 - (H21*$S21) -> 343663.38 | Q21: =IF(MOD($A21,7)=0,O21, MAX(0,(-K21 + S21/(I21+T21))*O21)) -> 66291.664 | R21: =IF(MOD($A21,7)=0,P21, MAX(0,(-L21 + T21/(J21+U21))*P21)) -> 0 | S21: =$B$11*B21 -> 1000000 | T21: =I21*$B$8 -> 70000.146 | U21: =J21*$B$7 -> 343663.38 | V21: =D21*$B$9 -> 1249009.6 | W21: =C21+U21+T21 -> 10005250 | X21: =0.15 * (Q21+R21+ IF(MOD(A21,7)=0,SUM(V15:V21),0)) -> 9943.7495 | Y21: =B21+U21+T21+V21-X21-S21 -> 20652729 | Z21: =((1 +$B$10)^$A21) - 1 -> 0.02 | AA21: =$B$16 * (1 + Z21) -> 20400000
A22: 2 | B22: =IF($A22=1,$B$16,Y21) -> 20652729 | C22: =IF(OR($A22=1, MOD($A22,7)=1),$B$4*$B22, I21+T21+J21+U21-(S21+X21)) -> 8995306.3 | D22: =IF(OR($A22=1, MOD($A22,7)=1),$B$3*$B22, D21+V21) -> 11657423 | E22: =C22/B22 -> 0.43555048 | F22: =D22/B22 -> 0.56444952 | G22: =MAX(0.05, $B$5 * EXP(-LN(2) * MAX(0, F22 - $B$15) / 0.1)) -> 0.094322017 | H22: =1-G22 -> 0.90567798 | I22: =C22*G22 -> 848455.43 | J22: =C22*H22 -> 8146850.8 | K22: =- ((I22+T22)/$W22 - MAX(0.05, $B$5 * EXP(-LN(2) * MAX(0, (($D22+$V22)/($B22+$T22+$U22+$V22-$S22)) - $B$15) / 0.1))) -> -0.027988526 | L22: =- ((J22+U22)/$W22 - (1 - MAX(0.05, $B$5 * EXP(-LN(2) * MAX(0, (($D22+$V22)/($B22+$T22+$U22+$V22-$S22)) - $B$15) / 0.1)))) -> 0.027988526 | M22: =IF(OR($A22=1, MOD($A22,7)=1), I22, (M21 * MIN(1, 1+(K22/G22))) + ($C22)*(MAX((K22),0))) - G22*$S22 -> 532546.05 | N22: =IF(OR($A22=1, MOD($A22,7)=1), J22, (N21 * MIN(1, 1+(L22/H22))) + ($C22)*(MAX((L22),0))) - H22*$S22 -> 7012371.9 | O22: =(I22+T22) - M22 - (G22*$S22) -> 277900.91 | P22: =(J22+U22) - N22 - (H22*$S22) -> 525116.84 | Q22: =IF(MOD($A22,7)=0,O22, MAX(0,(-K22 + S22/(I22+T22))*O22)) -> 323878.13 | R22: =IF(MOD($A22,7)=0,P22, MAX(0,(-L22 + T22/(J22+U22))*P22)) -> 0 | S22: =$B$11*B22 -> 1032636.5 | T22: =I22*$B$8 -> 59391.88 | U22: =J22*$B$7 -> 325874.03 | V22: =D22*$B$9 -> 1398890.8 | W22: =C22+U22+T22 -> 9380572.2 | X22: =0.15 * (Q22+R22+ IF(MOD(A22,7)=0,SUM(V16:V22),0)) -> 48581.719 | Y22: =B22+U22+T22+V22-X22-S22 -> 21355668 | Z22: =((1 +$B$10)^$A22) - 1 -> 0.0404 | AA22: =$B$16 * (1 + Z22) -> 20808000
A23: 3 | B23: =IF($A23=1,$B$16,Y22) -> 21355668 | C23: =IF(OR($A23=1, MOD($A23,7)=1),$B$4*$B23, I22+T22+J22+U22-(S22+X22)) -> 8299354 | D23: =IF(OR($A23=1, MOD($A23,7)=1),$B$3*$B23, D22+V22) -> 13056314 | E23: =C23/B23 -> 0.38862535 | F23: =D23/B23 -> 0.61137465 | G23: =MAX(0.05, $B$5 * EXP(-LN(2) * MAX(0, F23 - $B$15) / 0.1)) -> 0.068132506 | H23: =1-G23 -> 0.93186749 | I23: =C23*G23 -> 565455.79 | J23: =C23*H23 -> 7733898.2 | K23: =- ((I23+T23)/$W23 - MAX(0.05, $B$5 * EXP(-LN(2) * MAX(0, (($D23+$V23)/($B23+$T23+$U23+$V23-$S23)) - $B$15) / 0.1))) -> -0.01996037 | L23: =- ((J23+U23)/$W23 - (1 - MAX(0.05, $B$5 * EXP(-LN(2) * MAX(0, (($D23+$V23)/($B23+$T23+$U23+$V23-$S23)) - $B$15) / 0.1)))) -> 0.01996037 | M23: =IF(OR($A23=1, MOD($A23,7)=1), I23, (M22 * MIN(1, 1+(K23/G23))) + ($C23)*(MAX((K23),0))) - G23*$S23 -> 303778.48 | N23: =IF(OR($A23=1, MOD($A23,7)=1), J23, (N22 * MIN(1, 1+(L23/H23))) + ($C23)*(MAX((L23),0))) - H23*$S23 -> 6182997.5 | O23: =(I23+T23) - M23 - (G23*$S23) -> 228508.45 | P23: =(J23+U23) - N23 - (H23*$S23) -> 865224.04 | Q23: =IF(MOD($A23,7)=0,O23, MAX(0,(-K23 + S23/(I23+T23))*O23)) -> 407837.69 | R23: =IF(MOD($A23,7)=0,P23, MAX(0,(-L23 + T23/(J23+U23))*P23)) -> 0 | S23: =$B$11*B23 -> 1067783.4 | T23: =I23*$B$8 -> 39581.905 | U23: =J23*$B$7 -> 309355.93 | V23: =D23*$B$9 -> 1566757.7 | W23: =C23+U23+T23 -> 8648291.8 | X23: =0.15 * (Q23+R23+ IF(MOD(A23,7)=0,SUM(V17:V23),0)) -> 61175.654 | Y23: =B23+U23+T23+V23-X23-S23 -> 22142404 | Z23: =((1 +$B$10)^$A23) - 1 -> 0.061208 | AA23: =$B$16 * (1 + Z23) -> 21224160
A24: 4 | B24: =IF($A24=1,$B$16,Y23) -> 22142404 | C24: =IF(OR($A24=1, MOD($A24,7)=1),$B$4*$B24, I23+T23+J23+U23-(S23+X23)) -> 7519332.8 | D24: =IF(OR($A24=1, MOD($A24,7)=1),$B$3*$B24, D23+V23) -> 14623072 | E24: =C24/B24 -> 0.33958972 | F24: =D24/B24 -> 0.66041028 | G24: =MAX(0.05, $B$5 * EXP(-LN(2) * MAX(0, F24 - $B$15) / 0.1)) -> 0.05 | H24: =1-G24 -> 0.95 | I24: =C24*G24 -> 375966.64 | J24: =C24*H24 -> 7143366.2 | K24: =- ((I24+T24)/$W24 - MAX(0.05, $B$5 * EXP(-LN(2) * MAX(0, (($D24+$V24)/($B24+$T24+$U24+$V24-$S24)) - $B$15) / 0.1))) -> -0.0013682189 | L24: =- ((J24+U24)/$W24 - (1 - MAX(0.05, $B$5 * EXP(-LN(2) * MAX(0, (($D24+$V24)/($B24+$T24+$U24+$V24-$S24)) - $B$15) / 0.1)))) -> 0.0013682189 | M24: =IF(OR($A24=1, MOD($A24,7)=1), I24, (M23 * MIN(1, 1+(K24/G24))) + ($C24)*(MAX((K24),0))) - G24*$S24 -> 240109.76 | N24: =IF(OR($A24=1, MOD($A24,7)=1), J24, (N23 * MIN(1, 1+(L24/H24))) + ($C24)*(MAX((L24),0))) - H24*$S24 -> 5141521.4 | O24: =(I24+T24) - M24 - (G24*$S24) -> 106818.53 | P24: =(J24+U24) - N24 - (H24*$S24) -> 1235815.2 | Q24: =IF(MOD($A24,7)=0,O24, MAX(0,(-K24 + S24/(I24+T24))*O24)) -> 294119.73 | R24: =IF(MOD($A24,7)=0,P24, MAX(0,(-L24 + T24/(J24+U24))*P24)) -> 2687.0222 | S24: =$B$11*B24 -> 1107120.2 | T24: =I24*$B$8 -> 26317.665 | U24: =J24*$B$7 -> 285734.65 | V24: =D24*$B$9 -> 1754768.6 | W24: =C24+U24+T24 -> 7831385.1 | X24: =0.15 * (Q24+R24+ IF(MOD(A24,7)=0,SUM(V18:V24),0)) -> 44521.012 | Y24: =B24+U24+T24+V24-X24-S24 -> 23057584 | Z24: =((1 +$B$10)^$A24) - 1 -> 0.08243216 | AA24: =$B$16 * (1 + Z24) -> 21648643
A25: 5 | B25: =IF($A25=1,$B$16,Y24) -> 23057584 | C25: =IF(OR($A25=1, MOD($A25,7)=1),$B$4*$B25, I24+T24+J24+U24-(S24+X24)) -> 6679743.9 | D25: =IF(OR($A25=1, MOD($A25,7)=1),$B$3*$B25, D24+V24) -> 16377840 | E25: =C25/B25 -> 0.28969834 | F25: =D25/B25 -> 0.71030166 | G25: =MAX(0.05, $B$5 * EXP(-LN(2) * MAX(0, F25 - $B$15) / 0.1)) -> 0.05 | H25: =1-G25 -> 0.95 | I25: =C25*G25 -> 333987.19 | J25: =C25*H25 -> 6345756.7 | K25: =- ((I25+T25)/$W25 - MAX(0.05, $B$5 * EXP(-LN(2) * MAX(0, (($D25+$V25)/($B25+$T25+$U25+$V25-$S25)) - $B$15) / 0.1))) -> -0.0013682189 | L25: =- ((J25+U25)/$W25 - (1 - MAX(0.05, $B$5 * EXP(-LN(2) * MAX(0, (($D25+$V25)/($B25+$T25+$U25+$V25-$S25)) - $B$15) / 0.1)))) -> 0.0013682189 | M25: =IF(OR($A25=1, MOD($A25,7)=1), I25, (M24 * MIN(1, 1+(K25/G25))) + ($C25)*(MAX((K25),0))) - G25*$S25 -> 175895.35 | N25: =IF(OR($A25=1, MOD($A25,7)=1), J25, (N24 * MIN(1, 1+(L25/H25))) + ($C25)*(MAX((L25),0))) - H25*$S25 -> 4055425.5 | O25: =(I25+T25) - M25 - (G25*$S25) -> 123826.99 | P25: =(J25+U25) - N25 - (H25*$S25) -> 1448926.2 | Q25: =IF(MOD($A25,7)=0,O25, MAX(0,(-K25 + S25/(I25+T25))*O25)) -> 399640.67 | R25: =IF(MOD($A25,7)=0,P25, MAX(0,(-L25 + T25/(J25+U25))*P25)) -> 3150.3876 | S25: =$B$11*B25 -> 1152879.2 | T25: =I25*$B$8 -> 23379.104 | U25: =J25*$B$7 -> 253830.27 | V25: =D25*$B$9 -> 1965340.8 | W25: =C25+U25+T25 -> 6956953.2 | X25: =0.15 * (Q25+R25+ IF(MOD(A25,7)=0,SUM(V19:V25),0)) -> 60418.658 | Y25: =B25+U25+T25+V25-X25-S25 -> 24086836 | Z25: =((1 +$B$10)^$A25) - 1 -> 0.1040808 | AA25: =$B$16 * (1 + Z25) -> 22081616
A26: 6 | B26: =IF($A26=1,$B$16,Y25) -> 24086836 | C26: =IF(OR($A26=1, MOD($A26,7)=1),$B$4*$B26, I25+T25+J25+U25-(S25+X25)) -> 5743655.4 | D26: =IF(OR($A26=1, MOD($A26,7)=1),$B$3*$B26, D25+V25) -> 18343181 | E26: =C26/B26 -> 0.2384562 | F26: =D26/B26 -> 0.7615438 | G26: =MAX(0.05, $B$5 * EXP(-LN(2) * MAX(0, F26 - $B$15) / 0.1)) -> 0.05 | H26: =1-G26 -> 0.95 | I26: =C26*G26 -> 287182.77 | J26: =C26*H26 -> 5456472.6 | K26: =- ((I26+T26)/$W26 - MAX(0.05, $B$5 * EXP(-LN(2) * MAX(0, (($D26+$V26)/($B26+$T26+$U26+$V26-$S26)) - $B$15) / 0.1))) -> -0.0013682189 | L26: =- ((J26+U26)/$W26 - (1 - MAX(0.05, $B$5 * EXP(-LN(2) * MAX(0, (($D26+$V26)/($B26+$T26+$U26+$V26-$S26)) - $B$15) / 0.1)))) -> 0.0013682189 | M26: =IF(OR($A26=1, MOD($A26,7)=1), I26, (M25 * MIN(1, 1+(K26/G26))) + ($C26)*(MAX((K26),0))) - G26*$S26 -> 110864.99 | N26: =IF(OR($A26=1, MOD($A26,7)=1), J26, (N25 * MIN(1, 1+(L26/H26))) + ($C26)*(MAX((L26),0))) - H26*$S26 -> 2919159.3 | O26: =(I26+T26) - M26 - (G26*$S26) -> 136203.48 | P26: =(J26+U26) - N26 - (H26*$S26) -> 1611447.5 | Q26: =IF(MOD($A26,7)=0,O26, MAX(0,(-K26 + S26/(I26+T26))*O26)) -> 534007.56 | R26: =IF(MOD($A26,7)=0,P26, MAX(0,(-L26 + T26/(J26+U26))*P26)) -> 3503.7561 | S26: =$B$11*B26 -> 1204341.8 | T26: =I26*$B$8 -> 20102.794 | U26: =J26*$B$7 -> 218258.9 | V26: =D26*$B$9 -> 2201181.7 | W26: =C26+U26+T26 -> 5982017.1 | X26: =0.15 * (Q26+R26+ IF(MOD(A26,7)=0,SUM(V20:V26),0)) -> 80626.697 | Y26: =B26+U26+T26+V26-X26-S26 -> 25241411 | Z26: =((1 +$B$10)^$A26) - 1 -> 0.12616242 | AA26: =$B$16 * (1 + Z26) -> 22523248
A27: 7 | B27: =IF($A27=1,$B$16,Y26) -> 25241411 | C27: =IF(OR($A27=1, MOD($A27,7)=1),$B$4*$B27, I26+T26+J26+U26-(S26+X26)) -> 4697048.6 | D27: =IF(OR($A27=1, MOD($A27,7)=1),$B$3*$B27, D26+V26) -> 20544363 | E27: =C27/B27 -> 0.18608502 | F27: =D27/B27 -> 0.81391498 | G27: =MAX(0.05, $B$5 * EXP(-LN(2) * MAX(0, F27 - $B$15) / 0.1)) -> 0.05 | H27: =1-G27 -> 0.95 | I27: =C27*G27 -> 234852.43 | J27: =C27*H27 -> 4462196.1 | K27: =- ((I27+T27)/$W27 - MAX(0.05, $B$5 * EXP(-LN(2) * MAX(0, (($D27+$V27)/($B27+$T27+$U27+$V27-$S27)) - $B$15) / 0.1))) -> -0.0013682189 | L27: =- ((J27+U27)/$W27 - (1 - MAX(0.05, $B$5 * EXP(-LN(2) * MAX(0, (($D27+$V27)/($B27+$T27+$U27+$V27-$S27)) - $B$15) / 0.1)))) -> 0.0013682189 | M27: =IF(OR($A27=1, MOD($A27,7)=1), I27, (M26 * MIN(1, 1+(K27/G27))) + ($C27)*(MAX((K27),0))) - G27*$S27 -> 44727.711 | N27: =IF(OR($A27=1, MOD($A27,7)=1), J27, (N26 * MIN(1, 1+(L27/H27))) + ($C27)*(MAX((L27),0))) - H27*$S27 -> 1726618.9 | O27: =(I27+T27) - M27 - (G27*$S27) -> 143460.86 | P27: =(J27+U27) - N27 - (H27*$S27) -> 1715098.1 | Q27: =IF(MOD($A27,7)=0,O27, MAX(0,(-K27 + S27/(I27+T27))*O27)) -> 143460.86 | R27: =IF(MOD($A27,7)=0,P27, MAX(0,(-L27 + T27/(J27+U27))*P27)) -> 1715098.1 | S27: =$B$11*B27 -> 1262070.6 | T27: =I27*$B$8 -> 16439.67 | U27: =J27*$B$7 -> 178487.85 | V27: =D27*$B$9 -> 2465323.5 | W27: =C27+U27+T27 -> 4891976.1 | X27: =0.15 * (Q27+R27+ IF(MOD(A27,7)=0,SUM(V21:V27),0)) -> 2168974.7 | Y27: =B27+U27+T27+V27-X27-S27 -> 24470617 | Z27: =((1 +$B$10)^$A27) - 1 -> 0.14868567 | AA27: =$B$16 * (1 + Z27) -> 22973713
A28: 8 | B28: =IF($A28=1,$B$16,Y27) -> 24470617 | C28: =IF(OR($A28=1, MOD($A28,7)=1),$B$4*$B28, I27+T27+J27+U27-(S27+X27)) -> 11735602 | D28: =IF(OR($A28=1, MOD($A28,7)=1),$B$3*$B28, D27+V27) -> 12735015 | E28: =C28/B28 -> 0.47957933 | F28: =D28/B28 -> 0.52042067 | G28: =MAX(0.05, $B$5 * EXP(-LN(2) * MAX(0, F28 - $B$15) / 0.1)) -> 0.10425826 | H28: =1-G28 -> 0.89574174 | I28: =C28*G28 -> 1223533.4 | J28: =C28*H28 -> 10512069 | K28: =- ((I28+T28)/$W28 - MAX(0.05, $B$5 * EXP(-LN(2) * MAX(0, (($D28+$V28)/($B28+$T28+$U28+$V28-$S28)) - $B$15) / 0.1))) -> -0.012444299 | L28: =- ((J28+U28)/$W28 - (1 - MAX(0.05, $B$5 * EXP(-LN(2) * MAX(0, (($D28+$V28)/($B28+$T28+$U28+$V28-$S28)) - $B$15) / 0.1)))) -> 0.012444299 | M28: =IF(OR($A28=1, MOD($A28,7)=1), I28, (M27 * MIN(1, 1+(K28/G28))) + ($C28)*(MAX((K28),0))) - G28*$S28 -> 1095970.2 | N28: =IF(OR($A28=1, MOD($A28,7)=1), J28, (N27 * MIN(1, 1+(L28/H28))) + ($C28)*(MAX((L28),0))) - H28*$S28 -> 9416100.9 | O28: =(I28+T28) - M28 - (G28*$S28) -> 85647.338 | P28: =(J28+U28) - N28 - (H28*$S28) -> 420482.74 | Q28: =IF(MOD($A28,7)=0,O28, MAX(0,(-K28 + S28/(I28+T28))*O28)) -> 81109.895 | R28: =IF(MOD($A28,7)=0,P28, MAX(0,(-L28 + T28/(J28+U28))*P28)) -> 0 | S28: =$B$11*B28 -> 1223530.8 | T28: =I28*$B$8 -> 85647.338 | U28: =J28*$B$7 -> 420482.74 | V28: =D28*$B$9 -> 1528201.8 | W28: =C28+U28+T28 -> 12241732 | X28: =0.15 * (Q28+R28+ IF(MOD(A28,7)=0,SUM(V22:V28),0)) -> 12166.484 | Y28: =B28+U28+T28+V28-X28-S28 -> 25269252 | Z28: =((1 +$B$10)^$A28) - 1 -> 0.17165938 | AA28: =$B$16 * (1 + Z28) -> 23433188
A29: 9 | B29: =IF($A29=1,$B$16,Y28) -> 25269252 | C29: =IF(OR($A29=1, MOD($A29,7)=1),$B$4*$B29, I28+T28+J28+U28-(S28+X28)) -> 11006035 | D29: =IF(OR($A29=1, MOD($A29,7)=1),$B$3*$B29, D28+V28) -> 14263217 | E29: =C29/B29 -> 0.43555048 | F29: =D29/B29 -> 0.56444952 | G29: =MAX(0.05, $B$5 * EXP(-LN(2) * MAX(0, F29 - $B$15) / 0.1)) -> 0.094322017 | H29: =1-G29 -> 0.90567798 | I29: =C29*G29 -> 1038111.4 | J29: =C29*H29 -> 9967923.3 | K29: =- ((I29+T29)/$W29 - MAX(0.05, $B$5 * EXP(-LN(2) * MAX(0, (($D29+$V29)/($B29+$T29+$U29+$V29-$S29)) - $B$15) / 0.1))) -> -0.027988526 | L29: =- ((J29+U29)/$W29 - (1 - MAX(0.05, $B$5 * EXP(-LN(2) * MAX(0, (($D29+$V29)/($B29+$T29+$U29+$V29-$S29)) - $B$15) / 0.1)))) -> 0.027988526 | M29: =IF(OR($A29=1, MOD($A29,7)=1), I29, (M28 * MIN(1, 1+(K29/G29))) + ($C29)*(MAX((K29),0))) - G29*$S29 -> 651586.52 | N29: =IF(OR($A29=1, MOD($A29,7)=1), J29, (N28 * MIN(1, 1+(L29/H29))) + ($C29)*(MAX((L29),0))) - H29*$S29 -> 8579853.4 | O29: =(I29+T29) - M29 - (G29*$S29) -> 340020.34 | P29: =(J29+U29) - N29 - (H29*$S29) -> 642496.65 | Q29: =IF(MOD($A29,7)=0,O29, MAX(0,(-K29 + S29/(I29+T29))*O29)) -> 396274.88 | R29: =IF(MOD($A29,7)=0,P29, MAX(0,(-L29 + T29/(J29+U29))*P29)) -> 0 | S29: =$B$11*B29 -> 1263462.6 | T29: =I29*$B$8 -> 72667.798 | U29: =J29*$B$7 -> 398716.93 | V29: =D29*$B$9 -> 1711586 | W29: =C29+U29+T29 -> 11477419 | X29: =0.15 * (Q29+R29+ IF(MOD(A29,7)=0,SUM(V23:V29),0)) -> 59441.232 | Y29: =B29+U29+T29+V29-X29-S29 -> 26129318 | Z29: =((1 +$B$10)^$A29) - 1 -> 0.19509257 | AA29: =$B$16 * (1 + Z29) -> 23901851
A30: 10 | B30: =IF($A30=1,$B$16,Y29) -> 26129318 | C30: =IF(OR($A30=1, MOD($A30,7)=1),$B$4*$B30, I29+T29+J29+U29-(S29+X29)) -> 10154516 | D30: =IF(OR($A30=1, MOD($A30,7)=1),$B$3*$B30, D29+V29) -> 15974803 | E30: =C30/B30 -> 0.38862535 | F30: =D30/B30 -> 0.61137465 | G30: =MAX(0.05, $B$5 * EXP(-LN(2) * MAX(0, F30 - $B$15) / 0.1)) -> 0.068132506 | H30: =1-G30 -> 0.93186749 | I30: =C30*G30 -> 691852.6 | J30: =C30*H30 -> 9462663 | K30: =- ((I30+T30)/$W30 - MAX(0.05, $B$5 * EXP(-LN(2) * MAX(0, (($D30+$V30)/($B30+$T30+$U30+$V30-$S30)) - $B$15) / 0.1))) -> -0.01996037 | L30: =- ((J30+U30)/$W30 - (1 - MAX(0.05, $B$5 * EXP(-LN(2) * MAX(0, (($D30+$V30)/($B30+$T30+$U30+$V30-$S30)) - $B$15) / 0.1)))) -> 0.01996037 | M30: =IF(OR($A30=1, MOD($A30,7)=1), I30, (M29 * MIN(1, 1+(K30/G30))) + ($C30)*(MAX((K30),0))) - G30*$S30 -> 371682.34 | N30: =IF(OR($A30=1, MOD($A30,7)=1), J30, (N29 * MIN(1, 1+(L30/H30))) + ($C30)*(MAX((L30),0))) - H30*$S30 -> 7565088.1 | O30: =(I30+T30) - M30 - (G30*$S30) -> 279587.14 | P30: =(J30+U30) - N30 - (H30*$S30) -> 1058628.3 | Q30: =IF(MOD($A30,7)=0,O30, MAX(0,(-K30 + S30/(I30+T30))*O30)) -> 499002 | R30: =IF(MOD($A30,7)=0,P30, MAX(0,(-L30 + T30/(J30+U30))*P30)) -> 0 | S30: =$B$11*B30 -> 1306465.9 | T30: =I30*$B$8 -> 48429.682 | U30: =J30*$B$7 -> 378506.52 | V30: =D30*$B$9 -> 1916976.3 | W30: =C30+U30+T30 -> 10581452 | X30: =0.15 * (Q30+R30+ IF(MOD(A30,7)=0,SUM(V24:V30),0)) -> 74850.3 | Y30: =B30+U30+T30+V30-X30-S30 -> 27091915 | Z30: =((1 +$B$10)^$A30) - 1 -> 0.21899442 | AA30: =$B$16 * (1 + Z30) -> 24379888
A31: 11 | B31: =IF($A31=1,$B$16,Y30) -> 27091915 | C31: =IF(OR($A31=1, MOD($A31,7)=1),$B$4*$B31, I30+T30+J30+U30-(S30+X30)) -> 9200135.6 | D31: =IF(OR($A31=1, MOD($A31,7)=1),$B$3*$B31, D30+V30) -> 17891779 | E31: =C31/B31 -> 0.33958972 | F31: =D31/B31 -> 0.66041028 | G31: =MAX(0.05, $B$5 * EXP(-LN(2) * MAX(0, F31 - $B$15) / 0.1)) -> 0.05 | H31: =1-G31 -> 0.95 | I31: =C31*G31 -> 460006.78 | J31: =C31*H31 -> 8740128.8 | K31: =- ((I31+T31)/$W31 - MAX(0.05, $B$5 * EXP(-LN(2) * MAX(0, (($D31+$V31)/($B31+$T31+$U31+$V31-$S31)) - $B$15) / 0.1))) -> -0.0013682189 | L31: =- ((J31+U31)/$W31 - (1 - MAX(0.05, $B$5 * EXP(-LN(2) * MAX(0, (($D31+$V31)/($B31+$T31+$U31+$V31-$S31)) - $B$15) / 0.1)))) -> 0.0013682189 | M31: =IF(OR($A31=1, MOD($A31,7)=1), I31, (M30 * MIN(1, 1+(K31/G31))) + ($C31)*(MAX((K31),0))) - G31*$S31 -> 293781.7 | N31: =IF(OR($A31=1, MOD($A31,7)=1), J31, (N30 * MIN(1, 1+(L31/H31))) + ($C31)*(MAX((L31),0))) - H31*$S31 -> 6290810 | O31: =(I31+T31) - M31 - (G31*$S31) -> 130695.77 | P31: =(J31+U31) - N31 - (H31*$S31) -> 1512058.1 | Q31: =IF(MOD($A31,7)=0,O31, MAX(0,(-K31 + S31/(I31+T31))*O31)) -> 359864.56 | R31: =IF(MOD($A31,7)=0,P31, MAX(0,(-L31 + T31/(J31+U31))*P31)) -> 3287.6546 | S31: =$B$11*B31 -> 1354595.7 | T31: =I31*$B$8 -> 32200.475 | U31: =J31*$B$7 -> 349605.15 | V31: =D31*$B$9 -> 2147013.5 | W31: =C31+U31+T31 -> 9581941.3 | X31: =0.15 * (Q31+R31+ IF(MOD(A31,7)=0,SUM(V25:V31),0)) -> 54472.832 | Y31: =B31+U31+T31+V31-X31-S31 -> 28211665 | Z31: =((1 +$B$10)^$A31) - 1 -> 0.24337431 | AA31: =$B$16 * (1 + Z31) -> 24867486
A32: 12 | B32: =IF($A32=1,$B$16,Y31) -> 28211665 | C32: =IF(OR($A32=1, MOD($A32,7)=1),$B$4*$B32, I31+T31+J31+U31-(S31+X31)) -> 8172872.7 | D32: =IF(OR($A32=1, MOD($A32,7)=1),$B$3*$B32, D31+V31) -> 20038793 | E32: =C32/B32 -> 0.28969834 | F32: =D32/B32 -> 0.71030166 | G32: =MAX(0.05, $B$5 * EXP(-LN(2) * MAX(0, F32 - $B$15) / 0.1)) -> 0.05 | H32: =1-G32 -> 0.95 | I32: =C32*G32 -> 408643.63 | J32: =C32*H32 -> 7764229.1 | K32: =- ((I32+T32)/$W32 - MAX(0.05, $B$5 * EXP(-LN(2) * MAX(0, (($D32+$V32)/($B32+$T32+$U32+$V32-$S32)) - $B$15) / 0.1))) -> -0.0013682189 | L32: =- ((J32+U32)/$W32 - (1 - MAX(0.05, $B$5 * EXP(-LN(2) * MAX(0, (($D32+$V32)/($B32+$T32+$U32+$V32-$S32)) - $B$15) / 0.1)))) -> 0.0013682189 | M32: =IF(OR($A32=1, MOD($A32,7)=1), I32, (M31 * MIN(1, 1+(K32/G32))) + ($C32)*(MAX((K32),0))) - G32*$S32 -> 215213.38 | N32: =IF(OR($A32=1, MOD($A32,7)=1), J32, (N31 * MIN(1, 1+(L32/H32))) + ($C32)*(MAX((L32),0))) - H32*$S32 -> 4961938.2 | O32: =(I32+T32) - M32 - (G32*$S32) -> 151506.14 | P32: =(J32+U32) - N32 - (H32*$S32) -> 1772806 | Q32: =IF(MOD($A32,7)=0,O32, MAX(0,(-K32 + S32/(I32+T32))*O32)) -> 488972.69 | R32: =IF(MOD($A32,7)=0,P32, MAX(0,(-L32 + T32/(J32+U32))*P32)) -> 3854.5964 | S32: =$B$11*B32 -> 1410583.3 | T32: =I32*$B$8 -> 28605.054 | U32: =J32*$B$7 -> 310569.16 | V32: =D32*$B$9 -> 2404655.1 | W32: =C32+U32+T32 -> 8512046.9 | X32: =0.15 * (Q32+R32+ IF(MOD(A32,7)=0,SUM(V26:V32),0)) -> 73924.092 | Y32: =B32+U32+T32+V32-X32-S32 -> 29470987 | Z32: =((1 +$B$10)^$A32) - 1 -> 0.26824179 | AA32: =$B$16 * (1 + Z32) -> 25364836
A33: 13 | B33: =IF($A33=1,$B$16,Y32) -> 29470987 | C33: =IF(OR($A33=1, MOD($A33,7)=1),$B$4*$B33, I32+T32+J32+U32-(S32+X32)) -> 7027539.5 | D33: =IF(OR($A33=1, MOD($A33,7)=1),$B$3*$B33, D32+V32) -> 22443448 | E33: =C33/B33 -> 0.2384562 | F33: =D33/B33 -> 0.7615438 | G33: =MAX(0.05, $B$5 * EXP(-LN(2) * MAX(0, F33 - $B$15) / 0.1)) -> 0.05 | H33: =1-G33 -> 0.95 | I33: =C33*G33 -> 351376.98 | J33: =C33*H33 -> 6676162.6 | K33: =- ((I33+T33)/$W33 - MAX(0.05, $B$5 * EXP(-LN(2) * MAX(0, (($D33+$V33)/($B33+$T33+$U33+$V33-$S33)) - $B$15) / 0.1))) -> -0.0013682189 | L33: =- ((J33+U33)/$W33 - (1 - MAX(0.05, $B$5 * EXP(-LN(2) * MAX(0, (($D33+$V33)/($B33+$T33+$U33+$V33-$S33)) - $B$15) / 0.1)))) -> 0.0013682189 | M33: =IF(OR($A33=1, MOD($A33,7)=1), I33, (M32 * MIN(1, 1+(K33/G33))) + ($C33)*(MAX((K33),0))) - G33*$S33 -> 135646.74 | N33: =IF(OR($A33=1, MOD($A33,7)=1), J33, (N32 * MIN(1, 1+(L33/H33))) + ($C33)*(MAX((L33),0))) - H33*$S33 -> 3571681.5 | O33: =(I33+T33) - M33 - (G33*$S33) -> 166649.16 | P33: =(J33+U33) - N33 - (H33*$S33) -> 1971655.7 | Q33: =IF(MOD($A33,7)=0,O33, MAX(0,(-K33 + S33/(I33+T33))*O33)) -> 653374.72 | R33: =IF(MOD($A33,7)=0,P33, MAX(0,(-L33 + T33/(J33+U33))*P33)) -> 4286.9537 | S33: =$B$11*B33 -> 1473549.4 | T33: =I33*$B$8 -> 24596.388 | U33: =J33*$B$7 -> 267046.5 | V33: =D33*$B$9 -> 2693213.7 | W33: =C33+U33+T33 -> 7319182.4 | X33: =0.15 * (Q33+R33+ IF(MOD(A33,7)=0,SUM(V27:V33),0)) -> 98649.251 | Y33: =B33+U33+T33+V33-X33-S33 -> 30883645 | Z33: =((1 +$B$10)^$A33) - 1 -> 0.29360663 | AA33: =$B$16 * (1 + Z33) -> 25872133
... A90: 70 | B90: =IF($A90=1,$B$16,Y89) -> 1.5511291e+08 | C90: =IF(OR($A90=1, MOD($A90,7)=1),$B$4*$B90, I89+T89+J89+U89-(S89+X89)) -> 28864189 | D90: =IF(OR($A90=1, MOD($A90,7)=1),$B$3*$B90, D89+V89) -> 1.2624872e+08 | E90: =C90/B90 -> 0.18608502 | F90: =D90/B90 -> 0.81391498 | G90: =MAX(0.05, $B$5 * EXP(-LN(2) * MAX(0, F90 - $B$15) / 0.1)) -> 0.05 | H90: =1-G90 -> 0.95 | I90: =C90*G90 -> 1443209.5 | J90: =C90*H90 -> 27420980 | K90: =- ((I90+T90)/$W90 - MAX(0.05, $B$5 * EXP(-LN(2) * MAX(0, (($D90+$V90)/($B90+$T90+$U90+$V90-$S90)) - $B$15) / 0.1))) -> -0.0013682189 | L90: =- ((J90+U90)/$W90 - (1 - MAX(0.05, $B$5 * EXP(-LN(2) * MAX(0, (($D90+$V90)/($B90+$T90+$U90+$V90-$S90)) - $B$15) / 0.1)))) -> 0.0013682189 | M90: =IF(OR($A90=1, MOD($A90,7)=1), I90, (M89 * MIN(1, 1+(K90/G90))) + ($C90)*(MAX((K90),0))) - G90*$S90 -> 274859.65 | N90: =IF(OR($A90=1, MOD($A90,7)=1), J90, (N89 * MIN(1, 1+(L90/H90))) + ($C90)*(MAX((L90),0))) - H90*$S90 -> 10610377 | O90: =(I90+T90) - M90 - (G90*$S90) -> 881592.2 | P90: =(J90+U90) - N90 - (H90*$S90) -> 10539579 | Q90: =IF(MOD($A90,7)=0,O90, MAX(0,(-K90 + S90/(I90+T90))*O90)) -> 881592.2 | R90: =IF(MOD($A90,7)=0,P90, MAX(0,(-L90 + T90/(J90+U90))*P90)) -> 10539579 | S90: =$B$11*B90 -> 7755645.5 | T90: =I90*$B$8 -> 101024.66 | U90: =J90*$B$7 -> 1096839.2 | V90: =D90*$B$9 -> 15149846 | W90: =C90+U90+T90 -> 30062053 | X90: =0.15 * (Q90+R90+ IF(MOD(A90,7)=0,SUM(V84:V90),0)) -> 13328731 | Y90: =B90+U90+T90+V90-X90-S90 -> 1.5037624e+08 | Z90: =((1 +$B$10)^$A90) - 1 -> 2.9995582 | AA90: =$B$16 * (1 + Z90) -> 79991164

Sheet 3. Backtest
A1: Variáveis Utilizadas | E1: 1. Retornos Históricos | J1: Valores por Fase da Vida (Obtidos na Primeira Parte)
A2: Parâmetro | B2: Valor padrão | C2: Descrição | E2: Ano | F2: Private Equity Returns | G2: S&P500 | H2: Treasury Bond (10 anos) | J2: Fase da Vida | K2: Jovem Profissional | L2: Familia em Crescimento | M2: Aposentadoria
A3: Peso_ILIQ | B3: =HLOOKUP($B$24,Tabela29[#All],4,FALSE) -> 0.52042067 | C3: % alvo do patrimônio em Ilíquidos | E3: 1995 | F3: 0.23906608 | G3: 0.37195199 | H3: 0.2348078 | J3: Idade Inicial | K3: 30 | L3: 40 | M3: 75
A4: Peso_LIQ | B4: =1 -B3 -> 0.47957933 | C4: % alvo do patrimônio em RV + RF | E4: 1996 | F4: 0.30387514 | G4: 0.22680966 | H4: 0.014286078 | J4: % Gastos | K4: 0.02 | L4: 0.04 | M4: 0.05
A5: Mix_RV_dentro_LIQ | B5: =HLOOKUP($B$24,Tabela29[#All],6,FALSE) / (HLOOKUP($B$24,Tabela29[#All],6,FALSE) + HLOOKUP($B$24,Tabela29[#All],5,FALSE)) -> 0.10425826 | C5: % inicial de alocação em RV dentro dos ativos Líquidos | E5: 1997 | F5: 0.28713348 | G5: 0.33103653 | H5: 0.099391303 | J5: % Base de ILIQ | K5: ='1. Dados Históricos'!AG12 -> 0.46245655 | L5: ='1. Dados Históricos'!AG23 -> 0.36245024 | M5: ='1. Dados Históricos'!Z34 -> 0.52042067
A6: Mix_RF_dentro_LIQ | B6: =1 -B5 -> 0.89574174 | C6: % inicial de alocação em RF /dentro dos ativos Líquidos | E6: 1998 | F6: 0.16816404 | G6: 0.28337953 | H6: 0.14921432 | J6: % Base de Renda Fixa | K6: ='1. Dados Históricos'!AI12 -> 0.41754344 | L6: ='1. Dados Históricos'!AI23 -> 0.49504976 | M6: ='1. Dados Históricos'!AB34 -> 0.42957833
A7: Taxa_RF | B7: 0.04 | C7: Rendimento da Renda Fixa | E7: 1999 | F7: 0.3862112 | G7: 0.20885351 | H7: -0.082542148 | J7: % Base de Renda Variável | K7: ='1. Dados Históricos'!AH12 -> 0.12 | L7: ='1. Dados Históricos'!AH23 -> 0.1425 | M7: ='1. Dados Históricos'!AA34 -> 0.05
A8: Taxa_RV | B8: 0.07 | C8: Rendimento da Renda variável | E8: 2000 | F8: 0.044529382 | G8: -0.09031819 | H8: 0.16655267 | J8: % MAX ILIQ | K8: 0.6 | L8: 0.5 | M8: 0.4 | N8: Limites Estabelecidos Empiricamente
A9: Taxa_ILIQ | B9: 0.12 | C9: Rendimento dos ilíquidos | E9: 2001 | F9: -0.1135096 | G9: -0.11849759 | H9: 0.055721812
A10: Inflação | B10: 0.02 | C10: Inflação | E10: 2002 | F10: -0.039531947 | G10: -0.21966048 | H10: 0.151164
A11: Gastos% | B11: =HLOOKUP($B$24,Tabela29[#All],3,FALSE) -> 0.05 | C11: % do patrimônio que o cliente gasta anualmente | E11: 2003 | F11: 0.24162203 | G11: 0.283558 | H11: 0.0037531859
A12: IR | B12: 0.15 | C12: Imposto sobre o ganho realizado | E12: 2004 | F12: 0.28527889 | G12: 0.10742776 | H12: 0.044906837
A13: ITCMD | B13: 0.04 | C13: Imposto sobre a herança | E13: 2005 | F13: 0.26575343 | G13: 0.048344775 | H13: 0.02867533
A14: Ano_Liquidez | B14: 7 | C14: Ciclo de travamento dos ilíquidos | E14: 2006 | F14: 0.37906171 | G14: 0.15612558 | H14: 0.019610012
A15: Peso_Max_ILIQ | B15: =HLOOKUP($B$24,Tabela29[#All],7,FALSE) -> 0.4 | C15: Acionador para reduzir risco (liquidity-aware) | E15: 2007 | F15: 0.25253221 | G15: 0.054847352 | H15: 0.10209922
A16: Patrimônio Inicial | B16: 20000000 | C16: Patrimônio inicial do cliente | E16: 2008 | F16: -0.28966923 | G16: -0.36552344 | H16: 0.2010128
A17: Expectativa de Vida | B17: 90 | C17: Expectativa de vida do cliente | E17: 2009 | F17: 0.17127188 | G17: 0.25935234 | H17: -0.11116695
A18: Idade Inicial | B18: =HLOOKUP($B$24,Tabela29[#All],2,FALSE) -> 75 | C18: Idade do cliente no momento de contratação | E18: 2010 | F18: 0.20782132 | G18: 0.14821092 | H18: 0.084629339
E19: 2011 | F19: 0.069234969 | G19: 0.020983747 | H19: 0.16035335
E20: 2012 | F20: 0.14355029 | G20: 0.15890585 | H20: 0.02971572
E21: 2013 | F21: 0.20681101 | G21: 0.32145086 | H21: -0.091045688
A22: Resultados | E22: 2014 | F22: 0.10044195 | G22: 0.13524422 | H22: 0.1074618
E23: 2015 | F23: 0.085955738 | G23: 0.013788916 | H23: 0.012842997
A24: Fase da Vida: | B24: Aposentadoria | E24: 2016 | F24: 0.11346904 | G24: 0.11773081 | H24: 0.0069055047
E25: 2017 | F25: 0.22423202 | G25: 0.21605481 | H25: 0.028017163
A26: Resultado Final | B26: =Y76 -> 63902544 | E26: 2018 | F26: 0.093120837 | G26: -0.042268693 | H26: -0.00016692386
A27: Retorno Final | B27: =(B26-B16)/B16 -> 2.1951272 | E27: 2019 | F27: 0.17272263 | G27: 0.3121168 | H27: 0.096356307
A28: Maior Drawdown | B28: =MIN(AA47:AA76) -> -0.55463279 | E28: 2020 | F28: 0.2294 | G28: 0.18023202 | H28: 0.11331898
A29: Herança (após ITCMD) | B29: =$L$6-$L$7 -> 0.35254976 | E29: 2021 | F29: 0.0923 | G29: 0.28468852 | H29: -0.044160344
E30: 2022 | F30: -0.1596 | G30: -0.18037506 | H30: -0.17828172
E31: 2023 | F31: 0.3021 | G31: 0.26060685 | H31: 0.0388
E32: 2024 | F32: 0.147 | G32: 0.24878611 | H32: -0.016371801
A46: Ano | B46: Patrimônio Inicial | C46: Patrimônio RF + RV Inicial | D46: Patrimônio ILIQ | E46: % RV + RF | F46: % ILIQ | G46: % RV (dentro de RF + RV) | H46: % RF (dentro de RF + RV) | I46: Patrimônio RV | J46: Patrimônio RF | K46: % Prevista Rebalanceamento RV | L46: % Prevista Rebalanceamento RF | M46: Custo Base RV | N46: Custo Base RF | O46: Lucro Total Latente RV | P46: Lucro Total Latente RF | Q46: Lucro Realizado RV | R46: Lucro Realizado RF | S46: Gastos | T46: Rendimento RV | U46: Rendimento RF | V46: Rendimento ILIQ | W46: Total RF + RV Antes dos Gastos e Impostos | X46: Impostos | Y46: Patrimônio Final | Z46: Retorno Acumulado | AA46: Drawdown
A47: {=_xlfn.SEQUENCE(30,,,1)} -> 1 | B47: =IF($A47=1,$B$16,Y46) -> 20000000 | C47: =IF(OR($A47=1, MOD($A47,7)=1),$B$4*$B47, I46+T46+J46+U46-(S46+X46)) -> 9591586.5 | D47: =IF(OR($A47=1, MOD($A47,7)=1),$B$3*$B47, D46+V46) -> 10408413 | E47: =C47/B47 -> 0.47957933 | F47: =D47/B47 -> 0.52042067 | G47: =MAX(0.05, $B$5 * EXP(-LN(2) * MAX(0, F47 - $B$15) / 0.1)) -> 0.05 | H47: =1-G47 -> 0.95 | I47: =C47*G47 -> 479579.33 | J47: =C47*H47 -> 9112007.2 | K47: =- ((I47+T47)/$W47 - MAX(0.05, $B$5 * EXP(-LN(2) * MAX(0, (($D47+$V47)/($B47+$T47+$U47+$V47-$S47)) - $B$15) / 0.1))) -> -0.0052464625 | L47: =- ((J47+U47)/$W47 - (1 - MAX(0.05, $B$5 * EXP(-LN(2) * MAX(0, (($D47+$V47)/($B47+$T47+$U47+$V47-$S47)) - $B$15) / 0.1)))) -> 0.0052464625 | M47: =IF(OR($A47=1, MOD($A47,7)=1), I47, (M46 * MIN(1, 1+(K47/G47))) + ($C47)*(MAX((K47),0))) - G47*$S47 -> 429579.33 | N47: =IF(OR($A47=1, MOD($A47,7)=1), J47, (N46 * MIN(1, 1+(L47/H47))) + ($C47)*(MAX((L47),0))) - H47*$S47 -> 8162007.2 | O47: =(I47+T47) - M47 - (G47*$S47) -> 178380.48 | P47: =(J47+U47) - N47 - (H47*$S47) -> 2139570.4 | Q47: =IF(MOD($A47,7)=0,O47, MAX(0,(-K47 + S47/(I47+T47))*O47)) -> 272047.39 | R47: =IF(MOD($A47,7)=0,P47, MAX(0,(-L47 + T47/(J47+U47))*P47)) -> 22695.188 | S47: =$B$11*B47 -> 1000000 | T47: =I47*G3 -> 178380.48 | U47: =J47*H3 -> 2139570.4 | V47: =D47*F3 -> 2488298.6 | W47: =C47+U47+T47 -> 11909537 | X47: =MAX(0, 0.15 * (IF(R47=0,-ABS(U47*L47),R47)+IF(Q47=0,-ABS(T47*K47),Q47)+ IF(MOD(A47,7)=0,SUM(V41:V47),0))) -> 44211.386 | Y47: =B47+U47+T47+V47-X47-S47 -> 23762038 | Z47: =(Y47-$B$16)/$B$16 -> 0.1881019 | AA47: =(Y47 - MAX($Y$47:Y47))/Y47 -> 0
A48: 2 | B48: =IF($A48=1,$B$16,Y47) -> 23762038 | C48: =IF(OR($A48=1, MOD($A48,7)=1),$B$4*$B48, I47+T47+J47+U47-(S47+X47)) -> 10865326 | D48: =IF(OR($A48=1, MOD($A48,7)=1),$B$3*$B48, D47+V47) -> 12896712 | E48: =C48/B48 -> 0.45725564 | F48: =D48/B48 -> 0.54274436 | G48: =MAX(0.05, $B$5 * EXP(-LN(2) * MAX(0, F48 - $B$15) / 0.1)) -> 0.05 | H48: =1-G48 -> 0.95 | I48: =C48*G48 -> 543266.3 | J48: =C48*H48 -> 10322060 | K48: =- ((I48+T48)/$W48 - MAX(0.05, $B$5 * EXP(-LN(2) * MAX(0, (($D48+$V48)/($B48+$T48+$U48+$V48-$S48)) - $B$15) / 0.1))) -> -0.009849497 | L48: =- ((J48+U48)/$W48 - (1 - MAX(0.05, $B$5 * EXP(-LN(2) * MAX(0, (($D48+$V48)/($B48+$T48+$U48+$V48-$S48)) - $B$15) / 0.1)))) -> 0.009849497 | M48: =IF(OR($A48=1, MOD($A48,7)=1), I48, (M47 * MIN(1, 1+(K48/G48))) + ($C48)*(MAX((K48),0))) - G48*$S48 -> 285551.43 | N48: =IF(OR($A48=1, MOD($A48,7)=1), J48, (N47 * MIN(1, 1+(L48/H48))) + ($C48)*(MAX((L48),0))) - H48*$S48 -> 7140328.4 | O48: =(I48+T48) - M48 - (G48*$S48) -> 321527.82 | P48: =(J48+U48) - N48 - (H48*$S48) -> 2200496.2 | Q48: =IF(MOD($A48,7)=0,O48, MAX(0,(-K48 + S48/(I48+T48))*O48)) -> 576335.37 | R48: =IF(MOD($A48,7)=0,P48, MAX(0,(-L48 + T48/(J48+U48))*P48)) -> 4224.3315 | S48: =$B$11*B48 -> 1188101.9 | T48: =I48*G4 -> 123218.04 | U48: =J48*H4 -> 147461.75 | V48: =D48*F4 -> 3918990.2 | W48: =C48+U48+T48 -> 11136006 | X48: =MAX(0, 0.15 * (IF(R48=0,-ABS(U48*L48),R48)+IF(Q48=0,-ABS(T48*K48),Q48)+ IF(MOD(A48,7)=0,SUM(V42:V48),0))) -> 87083.955 | Y48: =B48+U48+T48+V48-X48-S48 -> 26676522 | Z48: =(Y48-$B$16)/$B$16 -> 0.33382611 | AA48: =(Y48 - MAX($Y$47:Y48))/Y48 -> 0
A49: 3 | B49: =IF($A49=1,$B$16,Y48) -> 26676522 | C49: =IF(OR($A49=1, MOD($A49,7)=1),$B$4*$B49, I48+T48+J48+U48-(S48+X48)) -> 9860819.9 | D49: =IF(OR($A49=1, MOD($A49,7)=1),$B$3*$B49, D48+V48) -> 16815702 | E49: =C49/B49 -> 0.36964413 | F49: =D49/B49 -> 0.63035587 | G49: =MAX(0.05, $B$5 * EXP(-LN(2) * MAX(0, F49 - $B$15) / 0.1)) -> 0.05 | H49: =1-G49 -> 0.95 | I49: =C49*G49 -> 493041 | J49: =C49*H49 -> 9367778.9 | K49: =- ((I49+T49)/$W49 - MAX(0.05, $B$5 * EXP(-LN(2) * MAX(0, (($D49+$V49)/($B49+$T49+$U49+$V49-$S49)) - $B$15) / 0.1))) -> -0.0099040596 | L49: =- ((J49+U49)/$W49 - (1 - MAX(0.05, $B$5 * EXP(-LN(2) * MAX(0, (($D49+$V49)/($B49+$T49+$U49+$V49-$S49)) - $B$15) / 0.1)))) -> 0.0099040596 | M49: =IF(OR($A49=1, MOD($A49,7)=1), I49, (M48 * MIN(1, 1+(K49/G49))) + ($C49)*(MAX((K49),0))) - G49*$S49 -> 162297.75 | N49: =IF(OR($A49=1, MOD($A49,7)=1), J49, (N48 * MIN(1, 1+(L49/H49))) + ($C49)*(MAX((L49),0))) - H49*$S49 -> 5970855.7 | O49: =(I49+T49) - M49 - (G49*$S49) -> 427266.52 | P49: =(J49+U49) - N49 - (H49*$S49) -> 3060864.1 | Q49: =IF(MOD($A49,7)=0,O49, MAX(0,(-K49 + S49/(I49+T49))*O49)) -> 872642.18 | R49: =IF(MOD($A49,7)=0,P49, MAX(0,(-L49 + T49/(J49+U49))*P49)) -> 18193.098 | S49: =$B$11*B49 -> 1333826.1 | T49: =I49*G5 -> 163214.58 | U49: =J49*H5 -> 931075.75 | V49: =D49*F5 -> 4828351.2 | W49: =C49+U49+T49 -> 10955110 | X49: =MAX(0, 0.15 * (IF(R49=0,-ABS(U49*L49),R49)+IF(Q49=0,-ABS(T49*K49),Q49)+ IF(MOD(A49,7)=0,SUM(V43:V49),0))) -> 133625.29 | Y49: =B49+U49+T49+V49-X49-S49 -> 31131712 | Z49: =(Y49-$B$16)/$B$16 -> 0.55658562 | AA49: =(Y49 - MAX($Y$47:Y49))/Y49 -> 0
A50: 4 | B50: =IF($A50=1,$B$16,Y49) -> 31131712 | C50: =IF(OR($A50=1, MOD($A50,7)=1),$B$4*$B50, I49+T49+J49+U49-(S49+X49)) -> 9487658.8 | D50: =IF(OR($A50=1, MOD($A50,7)=1),$B$3*$B50, D49+V49) -> 21644053 | E50: =C50/B50 -> 0.30475866 | F50: =D50/B50 -> 0.69524134 | G50: =MAX(0.05, $B$5 * EXP(-LN(2) * MAX(0, F50 - $B$15) / 0.1)) -> 0.05 | H50: =1-G50 -> 0.95 | I50: =C50*G50 -> 474382.94 | J50: =C50*H50 -> 9013275.9 | K50: =- ((I50+T50)/$W50 - MAX(0.05, $B$5 * EXP(-LN(2) * MAX(0, (($D50+$V50)/($B50+$T50+$U50+$V50-$S50)) - $B$15) / 0.1))) -> -0.0055132132 | L50: =- ((J50+U50)/$W50 - (1 - MAX(0.05, $B$5 * EXP(-LN(2) * MAX(0, (($D50+$V50)/($B50+$T50+$U50+$V50-$S50)) - $B$15) / 0.1)))) -> 0.0055132132 | M50: =IF(OR($A50=1, MOD($A50,7)=1), I50, (M49 * MIN(1, 1+(K50/G50))) + ($C50)*(MAX((K50),0))) - G50*$S50 -> 66572.83 | N50: =IF(OR($A50=1, MOD($A50,7)=1), J50, (N49 * MIN(1, 1+(L50/H50))) + ($C50)*(MAX((L50),0))) - H50*$S50 -> 4544406.9 | O50: =(I50+T50) - M50 - (G50*$S50) -> 464411.25 | P50: =(J50+U50) - N50 - (H50*$S50) -> 4335022.5 | Q50: =IF(MOD($A50,7)=0,O50, MAX(0,(-K50 + S50/(I50+T50))*O50)) -> 1189945.4 | R50: =IF(MOD($A50,7)=0,P50, MAX(0,(-L50 + T50/(J50+U50))*P50)) -> 32360.807 | S50: =$B$11*B50 -> 1556585.6 | T50: =I50*G6 -> 134430.42 | U50: =J50*H6 -> 1344909.8 | V50: =D50*F6 -> 3639751.5 | W50: =C50+U50+T50 -> 10966999 | X50: =MAX(0, 0.15 * (IF(R50=0,-ABS(U50*L50),R50)+IF(Q50=0,-ABS(T50*K50),Q50)+ IF(MOD(A50,7)=0,SUM(V44:V50),0))) -> 183345.94 | Y50: =B50+U50+T50+V50-X50-S50 -> 34510873 | Z50: =(Y50-$B$16)/$B$16 -> 0.72554363 | AA50: =(Y50 - MAX($Y$47:Y50))/Y50 -> 0
A51: 5 | B51: =IF($A51=1,$B$16,Y50) -> 34510873 | C51: =IF(OR($A51=1, MOD($A51,7)=1),$B$4*$B51, I50+T50+J50+U50-(S50+X50)) -> 9227067.5 | D51: =IF(OR($A51=1, MOD($A51,7)=1),$B$3*$B51, D50+V50) -> 25283805 | E51: =C51/B51 -> 0.26736697 | F51: =D51/B51 -> 0.73263303 | G51: =MAX(0.05, $B$5 * EXP(-LN(2) * MAX(0, F51 - $B$15) / 0.1)) -> 0.05 | H51: =1-G51 -> 0.95 | I51: =C51*G51 -> 461353.38 | J51: =C51*H51 -> 8765714.2 | K51: =- ((I51+T51)/$W51 - MAX(0.05, $B$5 * EXP(-LN(2) * MAX(0, (($D51+$V51)/($B51+$T51+$U51+$V51-$S51)) - $B$15) / 0.1))) -> -0.014850733 | L51: =- ((J51+U51)/$W51 - (1 - MAX(0.05, $B$5 * EXP(-LN(2) * MAX(0, (($D51+$V51)/($B51+$T51+$U51+$V51-$S51)) - $B$15) / 0.1)))) -> 0.014850733 | M51: =IF(OR($A51=1, MOD($A51,7)=1), I51, (M50 * MIN(1, 1+(K51/G51))) + ($C51)*(MAX((K51),0))) - G51*$S51 -> -39477.458 | N51: =IF(OR($A51=1, MOD($A51,7)=1), J51, (N50 * MIN(1, 1+(L51/H51))) + ($C51)*(MAX((L51),0))) - H51*$S51 -> 3042169.1 | O51: =(I51+T51) - M51 - (G51*$S51) -> 510908.93 | P51: =(J51+U51) - N51 - (H51*$S51) -> 3360737.7 | Q51: =IF(MOD($A51,7)=0,O51, MAX(0,(-K51 + S51/(I51+T51))*O51)) -> 1588333.2 | R51: =IF(MOD($A51,7)=0,P51, MAX(0,(-L51 + T51/(J51+U51))*P51)) -> 0 | S51: =$B$11*B51 -> 1725543.6 | T51: =I51*G7 -> 96355.272 | U51: =J51*H7 -> -723540.88 | V51: =D51*F7 -> 9764888.6 | W51: =C51+U51+T51 -> 8599881.9 | X51: =MAX(0, 0.15 * (IF(R51=0,-ABS(U51*L51),R51)+IF(Q51=0,-ABS(T51*K51),Q51)+ IF(MOD(A51,7)=0,SUM(V45:V51),0))) -> 236638.22 | Y51: =B51+U51+T51+V51-X51-S51 -> 41686394 | Z51: =(Y51-$B$16)/$B$16 -> 1.0843197 | AA51: =(Y51 - MAX($Y$47:Y51))/Y51 -> 0
A52: 6 | B52: =IF($A52=1,$B$16,Y51) -> 41686394 | C52: =IF(OR($A52=1, MOD($A52,7)=1),$B$4*$B52, I51+T51+J51+U51-(S51+X51)) -> 6637700.1 | D52: =IF(OR($A52=1, MOD($A52,7)=1),$B$3*$B52, D51+V51) -> 35048694 | E52: =C52/B52 -> 0.15922942 | F52: =D52/B52 -> 0.84077058 | G52: =MAX(0.05, $B$5 * EXP(-LN(2) * MAX(0, F52 - $B$15) / 0.1)) -> 0.05 | H52: =1-G52 -> 0.95 | I52: =C52*G52 -> 331885 | J52: =C52*H52 -> 6305815.1 | K52: =- ((I52+T52)/$W52 - MAX(0.05, $B$5 * EXP(-LN(2) * MAX(0, (($D52+$V52)/($B52+$T52+$U52+$V52-$S52)) - $B$15) / 0.1))) -> 0.010575773 | L52: =- ((J52+U52)/$W52 - (1 - MAX(0.05, $B$5 * EXP(-LN(2) * MAX(0, (($D52+$V52)/($B52+$T52+$U52+$V52-$S52)) - $B$15) / 0.1)))) -> -0.010575773 | M52: =IF(OR($A52=1, MOD($A52,7)=1), I52, (M51 * MIN(1, 1+(K52/G52))) + ($C52)*(MAX((K52),0))) - G52*$S52 -> -73494.633 | N52: =IF(OR($A52=1, MOD($A52,7)=1), J52, (N51 * MIN(1, 1+(L52/H52))) + ($C52)*(MAX((L52),0))) - H52*$S52 -> 1028198.8 | O52: =(I52+T52) - M52 - (G52*$S52) -> 271188.4 | P52: =(J52+U52) - N52 - (H52*$S52) -> 4347762.9 | Q52: =IF(MOD($A52,7)=0,O52, MAX(0,(-K52 + S52/(I52+T52))*O52)) -> 1869358.1 | R52: =IF(MOD($A52,7)=0,P52, MAX(0,(-L52 + T52/(J52+U52))*P52)) -> 28264.242 | S52: =$B$11*B52 -> 2084319.7 | T52: =I52*G8 -> -29975.253 | U52: =J52*H8 -> 1050250.3 | V52: =D52*F8 -> 1560696.7 | W52: =C52+U52+T52 -> 7657975.2 | X52: =MAX(0, 0.15 * (IF(R52=0,-ABS(U52*L52),R52)+IF(Q52=0,-ABS(T52*K52),Q52)+ IF(MOD(A52,7)=0,SUM(V46:V52),0))) -> 284643.35 | Y52: =B52+U52+T52+V52-X52-S52 -> 41898402 | Z52: =(Y52-$B$16)/$B$16 -> 1.0949201 | AA52: =(Y52 - MAX($Y$47:Y52))/Y52 -> 0
A53: 7 | B53: =IF($A53=1,$B$16,Y52) -> 41898402 | C53: =IF(OR($A53=1, MOD($A53,7)=1),$B$4*$B53, I52+T52+J52+U52-(S52+X52)) -> 5289012.1 | D53: =IF(OR($A53=1, MOD($A53,7)=1),$B$3*$B53, D52+V52) -> 36609390 | E53: =C53/B53 -> 0.12623422 | F53: =D53/B53 -> 0.87376578 | G53: =MAX(0.05, $B$5 * EXP(-LN(2) * MAX(0, F53 - $B$15) / 0.1)) -> 0.05 | H53: =1-G53 -> 0.95 | I53: =C53*G53 -> 264450.61 | J53: =C53*H53 -> 5024561.5 | K53: =- ((I53+T53)/$W53 - MAX(0.05, $B$5 * EXP(-LN(2) * MAX(0, (($D53+$V53)/($B53+$T53+$U53+$V53-$S53)) - $B$15) / 0.1))) -> 0.0079038548 | L53: =- ((J53+U53)/$W53 - (1 - MAX(0.05, $B$5 * EXP(-LN(2) * MAX(0, (($D53+$V53)/($B53+$T53+$U53+$V53-$S53)) - $B$15) / 0.1)))) -> -0.0079038548 | M53: =IF(OR($A53=1, MOD($A53,7)=1), I53, (M52 * MIN(1, 1+(K53/G53))) + ($C53)*(MAX((K53),0))) - G53*$S53 -> -136437.05 | N53: =IF(OR($A53=1, MOD($A53,7)=1), J53, (N52 * MIN(1, 1+(L53/H53))) + ($C53)*(MAX((L53),0))) - H53*$S53 -> -970529.76 | O53: =(I53+T53) - M53 - (G53*$S53) -> 264804.9 | P53: =(J53+U53) - N53 - (H53*$S53) -> 4284894.9 | Q53: =IF(MOD($A53,7)=0,O53, MAX(0,(-K53 + S53/(I53+T53))*O53)) -> 264804.9 | R53: =IF(MOD($A53,7)=0,P53, MAX(0,(-L53 + T53/(J53+U53))*P53)) -> 4284894.9 | S53: =$B$11*B53 -> 2094920.1 | T53: =I53*G9 -> -31336.76 | U53: =J53*H9 -> 279977.67 | V53: =D53*F9 -> -4155517.2 | W53: =C53+U53+T53 -> 5537653.1 | X53: =MAX(0, 0.15 * (IF(R53=0,-ABS(U53*L53),R53)+IF(Q53=0,-ABS(T53*K53),Q53)+ IF(MOD(A53,7)=0,SUM(V47:V53),0))) -> 3989273.9 | Y53: =B53+U53+T53+V53-X53-S53 -> 31907332 | Z53: =(Y53-$B$16)/$B$16 -> 0.59536661 | AA53: =(Y53 - MAX($Y$47:Y53))/Y53 -> -0.31312772
A54: 8 | B54: =IF($A54=1,$B$16,Y53) -> 31907332 | C54: =IF(OR($A54=1, MOD($A54,7)=1),$B$4*$B54, I53+T53+J53+U53-(S53+X53)) -> 15302097 | D54: =IF(OR($A54=1, MOD($A54,7)=1),$B$3*$B54, D53+V53) -> 16605235 | E54: =C54/B54 -> 0.47957933 | F54: =D54/B54 -> 0.52042067 | G54: =MAX(0.05, $B$5 * EXP(-LN(2) * MAX(0, F54 - $B$15) / 0.1)) -> 0.05 | H54: =1-G54 -> 0.95 | I54: =C54*G54 -> 765104.84 | J54: =C54*H54 -> 14536992 | K54: =- ((I54+T54)/$W54 - MAX(0.05, $B$5 * EXP(-LN(2) * MAX(0, (($D54+$V54)/($B54+$T54+$U54+$V54-$S54)) - $B$15) / 0.1))) -> 0.016482198 | L54: =- ((J54+U54)/$W54 - (1 - MAX(0.05, $B$5 * EXP(-LN(2) * MAX(0, (($D54+$V54)/($B54+$T54+$U54+$V54-$S54)) - $B$15) / 0.1)))) -> -0.016482198 | M54: =IF(OR($A54=1, MOD($A54,7)=1), I54, (M53 * MIN(1, 1+(K54/G54))) + ($C54)*(MAX((K54),0))) - G54*$S54 -> 685336.51 | N54: =IF(OR($A54=1, MOD($A54,7)=1), J54, (N53 * MIN(1, 1+(L54/H54))) + ($C54)*(MAX((L54),0))) - H54*$S54 -> 13021394 | O54: =(I54+T54) - M54 - (G54*$S54) -> -168063.3 | P54: =(J54+U54) - N54 - (H54*$S54) -> 2197469.9 | Q54: =IF(MOD($A54,7)=0,O54, MAX(0,(-K54 + S54/(I54+T54))*O54)) -> 0 | R54: =IF(MOD($A54,7)=0,P54, MAX(0,(-L54 + T54/(J54+U54))*P54)) -> 14150.064 | S54: =$B$11*B54 -> 1595366.6 | T54: =I54*G10 -> -168063.3 | U54: =J54*H10 -> 2197469.9 | V54: =D54*F10 -> -656437.28 | W54: =C54+U54+T54 -> 17331503 | X54: =MAX(0, 0.15 * (IF(R54=0,-ABS(U54*L54),R54)+IF(Q54=0,-ABS(T54*K54),Q54)+ IF(MOD(A54,7)=0,SUM(V48:V54),0))) -> 1707.0017 | Y54: =B54+U54+T54+V54-X54-S54 -> 31683228 | Z54: =(Y54-$B$16)/$B$16 -> 0.58416139 | AA54: =(Y54 - MAX($Y$47:Y54))/Y54 -> -0.32241584
A55: 9 | B55: =IF($A55=1,$B$16,Y54) -> 31683228 | C55: =IF(OR($A55=1, MOD($A55,7)=1),$B$4*$B55, I54+T54+J54+U54-(S54+X54)) -> 15734430 | D55: =IF(OR($A55=1, MOD($A55,7)=1),$B$3*$B55, D54+V54) -> 15948798 | E55: =C55/B55 -> 0.49661701 | F55: =D55/B55 -> 0.50338299 | G55: =MAX(0.05, $B$5 * EXP(-LN(2) * MAX(0, F55 - $B$15) / 0.1)) -> 0.050920967 | H55: =1-G55 -> 0.94907903 | I55: =C55*G55 -> 801212.38 | J55: =C55*H55 -> 14933217 | K55: =- ((I55+T55)/$W55 - MAX(0.05, $B$5 * EXP(-LN(2) * MAX(0, (($D55+$V55)/($B55+$T55+$U55+$V55-$S55)) - $B$15) / 0.1))) -> -0.014204266 | L55: =- ((J55+U55)/$W55 - (1 - MAX(0.05, $B$5 * EXP(-LN(2) * MAX(0, (($D55+$V55)/($B55+$T55+$U55+$V55-$S55)) - $B$15) / 0.1)))) -> 0.014204266 | M55: =IF(OR($A55=1, MOD($A55,7)=1), I55, (M54 * MIN(1, 1+(K55/G55))) + ($C55)*(MAX((K55),0))) - G55*$S55 -> 413496.72 | N55: =IF(OR($A55=1, MOD($A55,7)=1), J55, (N54 * MIN(1, 1+(L55/H55))) + ($C55)*(MAX((L55),0))) - H55*$S55 -> 11741395 | O55: =(I55+T55) - M55 - (G55*$S55) -> 534238.81 | P55: =(J55+U55) - N55 - (H55*$S55) -> 1744374.9 | Q55: =IF(MOD($A55,7)=0,O55, MAX(0,(-K55 + S55/(I55+T55))*O55)) -> 830535.18 | R55: =IF(MOD($A55,7)=0,P55, MAX(0,(-L55 + T55/(J55+U55))*P55)) -> 1661.6807 | S55: =$B$11*B55 -> 1584161.4 | T55: =I55*G11 -> 227190.18 | U55: =J55*H11 -> 56047.141 | V55: =D55*F11 -> 3853581 | W55: =C55+U55+T55 -> 16017667 | X55: =MAX(0, 0.15 * (IF(R55=0,-ABS(U55*L55),R55)+IF(Q55=0,-ABS(T55*K55),Q55)+ IF(MOD(A55,7)=0,SUM(V49:V55),0))) -> 124829.53 | Y55: =B55+U55+T55+V55-X55-S55 -> 34111055 | Z55: =(Y55-$B$16)/$B$16 -> 0.70555276 | AA55: =(Y55 - MAX($Y$47:Y55))/Y55 -> -0.22829394
A56: 10 | B56: =IF($A56=1,$B$16,Y55) -> 34111055 | C56: =IF(OR($A56=1, MOD($A56,7)=1),$B$4*$B56, I55+T55+J55+U55-(S55+X55)) -> 14308676 | D56: =IF(OR($A56=1, MOD($A56,7)=1),$B$3*$B56, D55+V55) -> 19802379 | E56: =C56/B56 -> 0.41947328 | F56: =D56/B56 -> 0.58052672 | G56: =MAX(0.05, $B$5 * EXP(-LN(2) * MAX(0, F56 - $B$15) / 0.1)) -> 0.05 | H56: =1-G56 -> 0.95 | I56: =C56*G56 -> 715433.81 | J56: =C56*H56 -> 13593242 | K56: =- ((I56+T56)/$W56 - MAX(0.05, $B$5 * EXP(-LN(2) * MAX(0, (($D56+$V56)/($B56+$T56+$U56+$V56-$S56)) - $B$15) / 0.1))) -> -0.0028336361 | L56: =- ((J56+U56)/$W56 - (1 - MAX(0.05, $B$5 * EXP(-LN(2) * MAX(0, (($D56+$V56)/($B56+$T56+$U56+$V56-$S56)) - $B$15) / 0.1)))) -> 0.0028336361 | M56: =IF(OR($A56=1, MOD($A56,7)=1), I56, (M55 * MIN(1, 1+(K56/G56))) + ($C56)*(MAX((K56),0))) - G56*$S56 -> 304785.09 | N56: =IF(OR($A56=1, MOD($A56,7)=1), J56, (N55 * MIN(1, 1+(L56/H56))) + ($C56)*(MAX((L56),0))) - H56*$S56 -> 10161666 | O56: =(I56+T56) - M56 - (G56*$S56) -> 402228.53 | P56: =(J56+U56) - N56 - (H56*$S56) -> 2421731 | Q56: =IF(MOD($A56,7)=0,O56, MAX(0,(-K56 + S56/(I56+T56))*O56)) -> 867010.71 | R56: =IF(MOD($A56,7)=0,P56, MAX(0,(-L56 + T56/(J56+U56))*P56)) -> 6241.9177 | S56: =$B$11*B56 -> 1705552.8 | T56: =I56*G12 -> 76857.451 | U56: =J56*H12 -> 610429.52 | V56: =D56*F12 -> 5649200.7 | W56: =C56+U56+T56 -> 14995963 | X56: =MAX(0, 0.15 * (IF(R56=0,-ABS(U56*L56),R56)+IF(Q56=0,-ABS(T56*K56),Q56)+ IF(MOD(A56,7)=0,SUM(V50:V56),0))) -> 130987.89 | Y56: =B56+U56+T56+V56-X56-S56 -> 38611002 | Z56: =(Y56-$B$16)/$B$16 -> 0.93055011 | AA56: =(Y56 - MAX($Y$47:Y56))/Y56 -> -0.085141539
A57: 11 | B57: =IF($A57=1,$B$16,Y56) -> 38611002 | C57: =IF(OR($A57=1, MOD($A57,7)=1),$B$4*$B57, I56+T56+J56+U56-(S56+X56)) -> 13159423 | D57: =IF(OR($A57=1, MOD($A57,7)=1),$B$3*$B57, D56+V56) -> 25451580 | E57: =C57/B57 -> 0.34082054 | F57: =D57/B57 -> 0.65917946 | G57: =MAX(0.05, $B$5 * EXP(-LN(2) * MAX(0, F57 - $B$15) / 0.1)) -> 0.05 | H57: =1-G57 -> 0.95 | I57: =C57*G57 -> 657971.13 | J57: =C57*H57 -> 12501451 | K57: =- ((I57+T57)/$W57 - MAX(0.05, $B$5 * EXP(-LN(2) * MAX(0, (($D57+$V57)/($B57+$T57+$U57+$V57-$S57)) - $B$15) / 0.1))) -> -0.00090738667 | L57: =- ((J57+U57)/$W57 - (1 - MAX(0.05, $B$5 * EXP(-LN(2) * MAX(0, (($D57+$V57)/($B57+$T57+$U57+$V57-$S57)) - $B$15) / 0.1)))) -> 0.00090738667 | M57: =IF(OR($A57=1, MOD($A57,7)=1), I57, (M56 * MIN(1, 1+(K57/G57))) + ($C57)*(MAX((K57),0))) - G57*$S57 -> 202726.43 | N57: =IF(OR($A57=1, MOD($A57,7)=1), J57, (N56 * MIN(1, 1+(L57/H57))) + ($C57)*(MAX((L57),0))) - H57*$S57 -> 8339583.9 | O57: =(I57+T57) - M57 - (G57*$S57) -> 390526.66 | P57: =(J57+U57) - N57 - (H57*$S57) -> 2686328.1 | Q57: =IF(MOD($A57,7)=0,O57, MAX(0,(-K57 + S57/(I57+T57))*O57)) -> 1093355.9 | R57: =IF(MOD($A57,7)=0,P57, MAX(0,(-L57 + T57/(J57+U57))*P57)) -> 4207.1816 | S57: =$B$11*B57 -> 1930550.1 | T57: =I57*G13 -> 31809.466 | U57: =J57*H13 -> 358483.24 | V57: =D57*F13 -> 6763844.5 | W57: =C57+U57+T57 -> 13549715 | X57: =MAX(0, 0.15 * (IF(R57=0,-ABS(U57*L57),R57)+IF(Q57=0,-ABS(T57*K57),Q57)+ IF(MOD(A57,7)=0,SUM(V51:V57),0))) -> 164634.47 | Y57: =B57+U57+T57+V57-X57-S57 -> 43669955 | Z57: =(Y57-$B$16)/$B$16 -> 1.1834977 | AA57: =(Y57 - MAX($Y$47:Y57))/Y57 -> 0
A58: 12 | B58: =IF($A58=1,$B$16,Y57) -> 43669955 | C58: =IF(OR($A58=1, MOD($A58,7)=1),$B$4*$B58, I57+T57+J57+U57-(S57+X57)) -> 11454531 | D58: =IF(OR($A58=1, MOD($A58,7)=1),$B$3*$B58, D57+V57) -> 32215424 | E58: =C58/B58 -> 0.26229774 | F58: =D58/B58 -> 0.73770226 | G58: =MAX(0.05, $B$5 * EXP(-LN(2) * MAX(0, F58 - $B$15) / 0.1)) -> 0.05 | H58: =1-G58 -> 0.95 | I58: =C58*G58 -> 572726.53 | J58: =C58*H58 -> 10881804 | K58: =- ((I58+T58)/$W58 - MAX(0.05, $B$5 * EXP(-LN(2) * MAX(0, (($D58+$V58)/($B58+$T58+$U58+$V58-$S58)) - $B$15) / 0.1))) -> -0.0063174818 | L58: =- ((J58+U58)/$W58 - (1 - MAX(0.05, $B$5 * EXP(-LN(2) * MAX(0, (($D58+$V58)/($B58+$T58+$U58+$V58-$S58)) - $B$15) / 0.1)))) -> 0.0063174818 | M58: =IF(OR($A58=1, MOD($A58,7)=1), I58, (M57 * MIN(1, 1+(K58/G58))) + ($C58)*(MAX((K58),0))) - G58*$S58 -> 67937.132 | N58: =IF(OR($A58=1, MOD($A58,7)=1), J58, (N57 * MIN(1, 1+(L58/H58))) + ($C58)*(MAX((L58),0))) - H58*$S58 -> 6337624.8 | O58: =(I58+T58) - M58 - (G58*$S58) -> 485031.78 | P58: =(J58+U58) - N58 - (H58*$S58) -> 2683248.8 | Q58: =IF(MOD($A58,7)=0,O58, MAX(0,(-K58 + S58/(I58+T58))*O58)) -> 1602514 | R58: =IF(MOD($A58,7)=0,P58, MAX(0,(-L58 + T58/(J58+U58))*P58)) -> 4673.1862 | S58: =$B$11*B58 -> 2183497.7 | T58: =I58*G14 -> 89417.262 | U58: =J58*H14 -> 213392.31 | V58: =D58*F14 -> 12211634 | W58: =C58+U58+T58 -> 11757340 | X58: =MAX(0, 0.15 * (IF(R58=0,-ABS(U58*L58),R58)+IF(Q58=0,-ABS(T58*K58),Q58)+ IF(MOD(A58,7)=0,SUM(V52:V58),0))) -> 241078.08 | Y58: =B58+U58+T58+V58-X58-S58 -> 53759822 | Z58: =(Y58-$B$16)/$B$16 -> 1.6879911 | AA58: =(Y58 - MAX($Y$47:Y58))/Y58 -> 0
A59: 13 | B59: =IF($A59=1,$B$16,Y58) -> 53759822 | C59: =IF(OR($A59=1, MOD($A59,7)=1),$B$4*$B59, I58+T58+J58+U58-(S58+X58)) -> 9332764.4 | D59: =IF(OR($A59=1, MOD($A59,7)=1),$B$3*$B59, D58+V58) -> 44427058 | E59: =C59/B59 -> 0.1736011 | F59: =D59/B59 -> 0.8263989 | G59: =MAX(0.05, $B$5 * EXP(-LN(2) * MAX(0, F59 - $B$15) / 0.1)) -> 0.05 | H59: =1-G59 -> 0.95 | I59: =C59*G59 -> 466638.22 | J59: =C59*H59 -> 8866126.2 | K59: =- ((I59+T59)/$W59 - MAX(0.05, $B$5 * EXP(-LN(2) * MAX(0, (($D59+$V59)/($B59+$T59+$U59+$V59-$S59)) - $B$15) / 0.1))) -> 0.0020409102 | L59: =- ((J59+U59)/$W59 - (1 - MAX(0.05, $B$5 * EXP(-LN(2) * MAX(0, (($D59+$V59)/($B59+$T59+$U59+$V59-$S59)) - $B$15) / 0.1)))) -> -0.0020409102 | M59: =IF(OR($A59=1, MOD($A59,7)=1), I59, (M58 * MIN(1, 1+(K59/G59))) + ($C59)*(MAX((K59),0))) - G59*$S59 -> -47415.09 | N59: =IF(OR($A59=1, MOD($A59,7)=1), J59, (N58 * MIN(1, 1+(L59/H59))) + ($C59)*(MAX((L59),0))) - H59*$S59 -> 3770418 | O59: =(I59+T59) - M59 - (G59*$S59) -> 405247.63 | P59: =(J59+U59) - N59 - (H59*$S59) -> 3447341.2 | Q59: =IF(MOD($A59,7)=0,O59, MAX(0,(-K59 + S59/(I59+T59))*O59)) -> 2212157.5 | R59: =IF(MOD($A59,7)=0,P59, MAX(0,(-L59 + T59/(J59+U59))*P59)) -> 16065.254 | S59: =$B$11*B59 -> 2687991.1 | T59: =I59*G15 -> 25593.871 | U59: =J59*H15 -> 905224.56 | V59: =D59*F15 -> 11219263 | W59: =C59+U59+T59 -> 10263583 | X59: =MAX(0, 0.15 * (IF(R59=0,-ABS(U59*L59),R59)+IF(Q59=0,-ABS(T59*K59),Q59)+ IF(MOD(A59,7)=0,SUM(V53:V59),0))) -> 334233.41 | Y59: =B59+U59+T59+V59-X59-S59 -> 62887679 | Z59: =(Y59-$B$16)/$B$16 -> 2.144384 | AA59: =(Y59 - MAX($Y$47:Y59))/Y59 -> 0
... A76: 30 | B76: =IF($A76=1,$B$16,Y75) -> 61820115 | C76: =IF(OR($A76=1, MOD($A76,7)=1),$B$4*$B76, I75+T75+J75+U75-(S75+X75)) -> 24733877 | D76: =IF(OR($A76=1, MOD($A76,7)=1),$B$3*$B76, D75+V75) -> 37086238 | E76: =C76/B76 -> 0.40009432 | F76: =D76/B76 -> 0.59990568 | G76: =MAX(0.05, $B$5 * EXP(-LN(2) * MAX(0, F76 - $B$15) / 0.1)) -> 0.05 | H76: =1-G76 -> 0.95 | I76: =C76*G76 -> 1236693.8 | J76: =C76*H76 -> 23497183 | K76: =- ((I76+T76)/$W76 - MAX(0.05, $B$5 * EXP(-LN(2) * MAX(0, (($D76+$V76)/($B76+$T76+$U76+$V76-$S76)) - $B$15) / 0.1))) -> -0.012634343 | L76: =- ((J76+U76)/$W76 - (1 - MAX(0.05, $B$5 * EXP(-LN(2) * MAX(0, (($D76+$V76)/($B76+$T76+$U76+$V76-$S76)) - $B$15) / 0.1)))) -> 0.012634343 | M76: =IF(OR($A76=1, MOD($A76,7)=1), I76, (M75 * MIN(1, 1+(K76/G76))) + ($C76)*(MAX((K76),0))) - G76*$S76 -> 723925.7 | N76: =IF(OR($A76=1, MOD($A76,7)=1), J76, (N75 * MIN(1, 1+(L76/H76))) + ($C76)*(MAX((L76),0))) - H76*$S76 -> 19710780 | O76: =(I76+T76) - M76 - (G76*$S76) -> 665890.1 | P76: =(J76+U76) - N76 - (H76*$S76) -> 465256.62 | Q76: =IF(MOD($A76,7)=0,O76, MAX(0,(-K76 + S76/(I76+T76))*O76)) -> 1341173.6 | R76: =IF(MOD($A76,7)=0,P76, MAX(0,(-L76 + T76/(J76+U76))*P76)) -> 315.25947 | S76: =$B$11*B76 -> 3091005.7 | T76: =I76*G32 -> 307672.25 | U76: =J76*H32 -> -384691.21 | V76: =D76*F32 -> 5451677 | W76: =C76+U76+T76 -> 24656858 | X76: =MAX(0, 0.15 * (IF(R76=0,-ABS(U76*L76),R76)+IF(Q76=0,-ABS(T76*K76),Q76)+ IF(MOD(A76,7)=0,SUM(V70:V76),0))) -> 201223.33 | Y76: =B76+U76+T76+V76-X76-S76 -> 63902544 | Z76: =(Y76-$B$16)/$B$16 -> 2.1951272 | AA76: =(Y76 - MAX($Y$47:Y76))/Y76 -> -0.17019638
